Workbook

Sheet Задачи
A1: № | B1: Срок | C1: Задача | D1: Зачем / результат | E1: Ответственный | F1: Связанные компании (лист «Анализ») | G1: Статус | H1: Дата
A2: 1 | B2: Сегодня | C2: Сверить нашу цену за м² на 2–3 ходовых LED-экрана с бенчмарком и опубликовать на сайте «от … ₽/м²» + 2–3 примера «размер → итоговая цена» | D2: Открытые цены есть у Детектора, Экранпро, GTLight, MediaScreen. Клиент приходит уже с ценой в голове — без неё мы проигрываем на входе и теряем лиды после КП | E2: Андрей | F2: Детектор, ЭКРАНПРО, Электронные Системы, MEDIASCREEN | G2: Не начато
A3: 2 | B3: Сегодня | C3: Пересобрать гарантийный оффер: «до 5 лет» перестал быть отличием | D3: У Экранпро 5 лет + 10 лет техподдержки, у GTLight до 5 лет. Нужно добавить то, что можем выполнить: сроки выезда, подменный фонд, сервисный контракт — и зафиксировать в КП | E3: Андрей | F3: ЭКРАНПРО, Электронные Системы, АудиоВидеоСистемы | G3: Не начато
A4: 3 | B4: На этой неделе | C4: Ввести регламент «КП за 24 часа» для типовых запросов | D4: Бенчмарк: Интэч — 2 часа, DIXTEN — от 3 часов, АВС — 1 день. Скорость КП напрямую влияет на отвал после запроса | E4: Андрей + менеджеры | F4: Интэч Инкорпорейтед, Дикстен, АудиоВидеоСистемы | G4: Не начато
A5: 4 | B5: На этой неделе | C5: Подать заявки в партнёрские программы TrueConf и Addreality | D5: Пакеты «ВКС-комната под ключ» с ПО из реестра и «экран + контент-платформа по подписке» — вход в госсектор и повторная выручка | E5: Андрей | F5: Труконф, Эддреалити | G5: Не начато
A6: 5 | B6: На этой неделе | C6: «Тайный покупатель» по одному ТЗ: экран 3×2 м интерьер, 6×3 м улица, киоск 43" | D6: Узнать реальные цены, скорость ответа, гарантию, качество КП у прямых конкурентов | E6: Менеджер / ассистент | F6: Детектор, ЭКРАНПРО, 1000 Дюймов, Смарткиоск, Анкомп, ЭЙЧДИ | G6: Не начато
A7: 6 | B7: На этой неделе | C7: Прозвон музейных студий: «ваша концепция и контент — наше производство» | D7: У студий нет своего производства корпусов, киосков, LED — это партнёрский канал в растущий музейный сегмент | E7: Андрей | F7: Visuals, Банана Брэд, ФИЛИН ПРО, ТРИПЛАН, ПМТ, Метаформа, Викинг Проект | G7: Не начато
A8: 7 | B8: На этой неделе | C8: Вручную проверить 12 строк, где сайт не открылся (колонка Q, оранжевые в O) | D8: Сейчас в этих строках шаблонный текст, а не факты | E8: Ассистент / агент Chrome | F8: XCOM, ЛЕ-Интеграция, Видау, Видео ЛЕНД, ИНТЕР, БС-ГРУП, INTOKU, SubProject, СВ ТЕЛЕКОМ, Milestone, Аллегри, БС-Инжиниринг | G8: Не начато
A9: 8 | B9: В течение месяца | C9: Собрать пакеты «переговорная S/M/L» с фикс-ценой и сроком | D9: Готовый образец — SMART ROOMS: 7 пакетов от 159 000 до 5 800 000 ₽. Типовой пакет — понятный вход для клиента и для партнёров-интеграторов | E9: Андрей + менеджеры | F9: СМАРТ РУМС | G9: Не начато
A10: 9 | B10: В течение месяца | C10: Калькулятор стоимости LED-экрана на st-led | D10: Есть у Детектора, Экранпро, GTLight, 1000 Дюймов (там ещё −10% за заявку из калькулятора). Калькулятор = лидогенерация | E10: Андрей + разработчик | F10: Детектор, ЭКРАНПРО, Электронные Системы, 1000 Дюймов | G10: Не начато
A11: 10 | B11: В течение месяца | C11: Страница «Для интеграторов и дилеров» с конкретными условиями: скидки по уровням, сроки, WL, гарантия | D11: У Громвижн и Д2 партнёрские разделы без цифр — конкретика будет отличием. Модель кабинета дилера — у Future Vision | E11: Андрей | F11: ГРОМВИЖН, Д2 Групп, Future Vision, ЦС Проект | G11: Не начато
A12: 11 | B12: В течение месяца | C12: Прозвон AV-интеграторов с приоритетом A: WL-производство LED, киосков, корпусов | D12: Главный канал роста без расширения штата. Вести статусы в колонках R–V | E12: Менеджеры | F12: Фильтр: колонка M = «A», L = «Партнёр…» | G12: Не начато
A13: 12 | B13: В течение месяца | C13: Офферы конверсии: пилот / тест-драйв панели или киоска, лизинг, бесплатная 3D-визуализация | D13: Эти офферы есть у АВС, Optimus, Open Vision, Умного Века, 1000 Дюймов — сейчас у нас их нет | E13: Андрей | F13: АудиоВидеоСистемы, ОПТИМУС КОНСАЛТ, ОПЕН ВИЖН, Умный Век | G13: Не начато
... A20: 19 | B20: Доработка таблицы | C20: Найти ЛПР и контакты для компаний с приоритетом A и заполнить колонки R–S | D20: Без ЛПР прозвон превращается в звонки на ресепшн | E20: Ассистент / менеджеры | F20: Фильтр: колонка M = «A» | G20: Не начато

Sheet Анализ >50 млн
A1: Компания | B1: Тип | C1: Сайт | D1: ИНН | E1: Выручка 2023, млн ₽ | F1: Регион | G1: Чем занимается | H1: Ключевые товары / услуги | I1: Предложения клиентам | J1: Что применить Simple Touch в ближайшее время | K1: Соцсети и о чём пишут | L1: ★ Кем компания является для нас | M1: ★ Приоритет (A — сейчас, B — в течение месяца, C — не сейчас) | N1: ★ Первый шаг / точка входа | O1: Статус проверки данных | P1: Источники | Q1: ⚑ Что доработать в строке | R1: ЛПР (ФИО, должность) | S1: Контакт (телефон / e-mail / TG) | T1: Статус работы | U1: Дата следующего шага | V1: Комментарий по контакту
A2: КРОК | B2: Широкопрофильный | C2: croc.ru | D2: 7701004101 | E2: =INDEX(База!$E:$E,2) -> 26652 | F2: Москва | G2: КРОК — технологический партнёр с 30-летним опытом: ИТ-инфраструктура, внедрение информационных систем, цифровая трансформация крупных предприятий (AV — одно из направлений, на главной странице не выделено отдельно). | H2: ИТ-консалтинг и стратегия, системная интеграция, инфраструктурные решения (AV-направление отдельно на главной не детализировано — требуется отдельная AV-страница) | I2: Нет цен/гарантий на главной. Есть бесплатные форматы: демо-дни, кейс-лаборатории | J2: У КРОК демо-дни и кейс-лаборатории как формат вовлечения B2B-клиентов — Simple Touch может перенять формат открытых демо-дней в шоуруме | K2: Telegram (закрытая ссылка-приглашение), VK vk.com/crocincor, YouTube, Habr habr.com/ru/companies/croc — активность не детализирована (на Habr всего 1 пост в профиле) | L2: Заказчик субподряда / WL-производства | M2: B | N2: Выйти на руководителя AV-направления или закупки; предложить WL-производство нестандартных конструкций с гарантией до 5 лет | O2: Проверено, данные изменены | P2: https://croc.ru/
A3: XCOM | B3: Широкопрофильный | C3: xcom.ru | D3: 7743553167 | E3: =INDEX(База!$E:$E,3) -> 15243 | F3: Москва | G3: ИТ-интегратор и поставщик оборудования для корпораций и госсектора | H3: Видеостены, LED, ВКС, ситуационные центры, СКС, ИТ-инфраструктура | I3: Комплексный проект «под ключ»: аудит → проект → поставка → монтаж → сервис; тендеры 44/223-ФЗ | J3: Страница «Для интеграторов» на сайте: производство нестандартных корпусов, стоек, LED-конструкций и брендирования под их проекты (White Label) | K3: Не проверено — открыть сайт, найти иконки соцсетей, оценить частоту постов | L3: Заказчик субподряда / WL-производства | M3: B | N3: Выйти на руководителя AV-направления или закупки; предложить WL-производство нестандартных конструкций с гарантией до 5 лет | O3: Сайт не открывается (пустая белая страница, контент не загружается) | Q3: Сайт не открылся — проверить вручную или найти актуальный домен по ИНН; колонки G–K сейчас шаблонные, не факты
A4: ЛАНИТ | B4: Широкопрофильный | C4: lanit.ru | D4: 7727004113 | E4: =INDEX(База!$E:$E,4) -> 14416 | F4: Москва | G4: ЛАНИТ — крупнейший российский ИТ-холдинг с 1989 г. (14 000+ специалистов): системная интеграция, разработка ПО, консалтинг, аутсорсинг; «Мультимедиа» упомянута как одна из услуг блока «Инфраструктура и системная интеграция» без деталей. | H4: Мультимедиа (без деталей на главной), ИТ-инфраструктура и системная интеграция, разработка ПО, инженерные системы, решения для удалённой работы, собственные платформы (ONPLATFORM, ONCLOUD, Онланта ИИ Хаб) | I4: Нет цен на сайте — предложение обсуждения по темам инноваций и инфраструктуры | J4: ЛАНИТ — гигант, мультимедиа/AV у них непубличное направление внутри профильных «дочек»; выходить точечно на конкретную дочернюю компанию, а не на головной сайт | K4: Telegram t.me/Lanit\_life, VK vk.com/lanit\_life, Habr habrahabr.ru/company/lanit, Дзен dzen.ru/lanit — активность не детализирована | L4: Заказчик субподряда / WL-производства | M4: B | N4: Выйти на руководителя AV-направления или закупки; предложить WL-производство нестандартных конструкций с гарантией до 5 лет | O4: Проверено, данные изменены | P4: https://lanit.ru/
A5: СТЕП ЛОДЖИК | B5: Широкопрофильный | C5: step.ru | D5: 7730081654 | E5: =INDEX(База!$E:$E,6) -> 9322 | F5: Москва | G5: STEP LOGIC — системный интегратор с 1992 г.: сетевая и системная интеграция для госсектора, телекома, промышленности, финансов; есть направление «Мультимедиа-решения и унифицированные коммуникации» (студии видеоприсутствия — кейс L'Oreal). | H5: Мультимедиа-решения и унифицированные коммуникации, студии видеоприсутствия, мониторинговые системы, инженерные и вычислительные системы, информационная безопасность, контакт-центры | I5: Нет на сайте цен/акций — только направления компетенций и портфолио | J5: Кейс студии видеоприсутствия L'Oreal — точка входа для видеостен/LED в подобные корпоративные студии | K5: Habr habr.com/ru/company/step\_logic — активность не детализирована. Telegram/VK/YouTube/Дзен/Rutube не найдены | L5: Заказчик субподряда / WL-производства | M5: B | N5: Выйти на руководителя AV-направления или закупки; предложить WL-производство нестандартных конструкций с гарантией до 5 лет | O5: Проверено 25.09.2026 | P5: https://step.ru/
A6: АУВИКС | B6: Дистрибьютор | C6: auvix.ru | D6: 7708651718 | E6: =INDEX(База!$E:$E,7) -> 8933 | F6: Москва | G6: AUVIX — крупнейший российский дистрибьютор профессионального AV-оборудования: презентационные и звуковые решения, конференц-залы и ситуационные центры «под ключ». | H6: Проекторы и экраны, звуковое оборудование, интерактивные доски, AV-коммутация и ВКС, LED-экраны, оборудование для записи и трансляции | I6: «5000+ дилеров работают с нами», доставка и самовывоз, сервисная поддержка. Точные дилерские условия/скидки/демо-фонд не опубликованы — форма «Стать дилером» | J6: У AUVIX 5000+ дилеров в базе — масштаб дилерской сети как ориентир; сравнить их дилерский онбординг с нашим при регистрации | K6: Telegram t.me/auvix, VK vk.com/auvix, YouTube, Дзен dzen.ru/auvix — активность не детализирована | L6: Поставщик / бенчмарк партнёрской программы | M6: B | N6: Запросить дилерские условия и сравнить с закупкой через Шанхай | O6: Проверено, данные изменены | P6: https://auvix.ru/
A7: АВИЛЕКС | B7: Интегратор АВ | C7: avilex.ru | D7: 7731625191 | E7: =INDEX(База!$E:$E,8) -> 4100 | F7: Москва | G7: Авилекс — системный интегратор «конвергенции информационных и аудиовизуальных технологий»: комплексные решения высшей категории сложности для госорганов и бизнеса. | H7: Конкретный каталог на сайте не раскрыт — только общие формулировки о комплексных AV/ИТ-решениях | I7: Нет на сайте: цен, гарантий, демо | J7: Сайт закрытый, без каталога и цен — типичный признак крупного госзаказчика; предложить WL-пакет через личный контакт, а не через сайт | K7: Соцсетей на сайте нет | L7: Партнёр: покупатель LED / киосков / стендов под своим брендом (WL) | M7: B | N7: Звонок собственнику/коммерческому: WL-производство LED-экранов, киосков, корпусов под их бренд по дилерской цене | O7: Проверено 25.09.2026 | P7: https://avilex.ru/
A8: Полимедиа | B8: Интегратор АВ | C8: polymedia.ru | D8: 9705117847 | E8: =INDEX(База!$E:$E,9) -> 3975 | F8: Москва | G8: Polymedia — системный интегратор и ИТ-компания: информационно-аналитические решения, ситуационные центры, мультимедийные инсталляции, дистрибуция AV; 18 000+ проектов. | H8: Аналитические системы (хранилища данных), ситуационные центры и диспетчерские, мультимедийные инсталляции, дистрибуция AV-оборудования с ИИ, аренда для мероприятий, техподдержка | I8: Нет на сайте: цен, гарантий, демо, вебинаров — расчёт стоимости и консультация по заявке | J8: Кейс с НИУ ВШЭ («Аудитория гибридного формата») подтверждён, также МГТУ им. Баумана — подкрепляет идею пакета «интерактивный класс/аудитория» для вузов | K8: VK vk.com/av\_polymedia, Telegram t.me/AV\_Polymedia, YouTube — активность не детализирована | L8: Партнёр: покупатель LED / киосков / стендов под своим брендом (WL) | M8: B | N8: Звонок собственнику/коммерческому: WL-производство LED-экранов, киосков, корпусов под их бренд по дилерской цене | O8: Проверено, данные изменены | P8: https://polymedia.ru/
A9: Лайв Саунд | B9: Интегратор АВ | C9: livesound.ru | D9: 9724154876 | E9: =INDEX(База!$E:$E,11) -> 3182 | F9: Москва | G9: Лайв Саунд — московский интегратор мультимедийных систем (с 1997 г., 28 лет на рынке, 200+ проектов): звук, видео, сценические технологии, свет. | H9: Звуковые системы (оповещение, конференц-звук, концертное/театральное озвучивание, спорт); видеостены, проекция, LED-экраны, медиафасады; сценическая механика и конструкции; архитектурное/сценическое/декоративное освещение. | I9: Гарантия до 3 лет; проектирование и техдокументация; монтаж и пусконаладка; техподдержка и обслуживание. Цен «от», скидок или акций с цифрами на сайте нет. | J9: Сравнить гарантию: у Simple Touch — до 5 лет против 3 лет у Лайв Саунд; использовать длинную гарантию как конкурентное преимущество. | K9: Соцсетей на сайте нет. | L9: Низкая релевантность (звук) | M9: C | N9: Звонок собственнику/коммерческому: WL-производство LED-экранов, киосков, корпусов под их бренд по дилерской цене | O9: Проверено 25.09.2026 | P9: https://livesound.ru/
A10: Аметист | B10: Широкопрофильный | C10: ametist.tech | D10: 7810819986 | E10: =INDEX(База!$E:$E,12) -> 3137 | F10: Санкт-Петербург | G10: Аметист — федеральный системный интегратор: ИТ-инфраструктура, ЦОД, инженерная инфраструктура, мультимедиа, ИБ; акцент на импортозамещение. | H10: Системная интеграция, проектирование и строительство ЦОД, инженерная инфраструктура, мультимедийные решения, информационная безопасность, поставка ИТ-оборудования | I10: Нет прайсов и гарантий на сайте — «стоимость каждого проекта рассчитывается индивидуально». Партнёрской программы не найдено | J10: Акцент на импортозамещение — предложить Simple Touch как отечественного производителя (своё производство в Москве) в рамках их программы импортозамещения | K10: VK vk.com/ametist.tech, RuTube, VK Video — активность не детализирована. Telegram/YouTube/Дзен/Habr не найдены | L10: Заказчик субподряда / WL-производства | M10: B | N10: Выйти на руководителя AV-направления или закупки; предложить WL-производство нестандартных конструкций с гарантией до 5 лет | O10: Проверено 25.09.2026 | P10: https://ametist.tech/
A11: СИТИСИ Кэпитал | B11: Дистрибьютор | C11: ctccapital.ru | D11: 6732026311 | E11: =INDEX(База!$E:$E,13) -> 2555 | G11: CTC CAPITAL — московский дистрибьютор профессионального АВ-оборудования (с 1992 г.): подбор, конфигурация и монтаж решений по всей РФ. | H11: Проекторы, проф. дисплеи, LED-экраны, презентационные системы, коммутационное оборудование, камеры, интерактивные решения, проф. звук и свет, медицинские мониторы, hi-fi, экраны, сценическое оборудование; 50+ представленных брендов (Barco, Samsung, Unilumin и др.). | I11: Скидка до 9% на коммутационное оборудование при комплексных решениях; 2 шоурума в Москве (200+ единиц техники на постоянной экспозиции); аренда оборудования с техподдержкой; партнёрская B2B-программа по регистрации. | J11: Перенять модель постоянно действующего шоурума (200+ единиц техники «вживую») — открыть/расширить демо-зону Simple Touch, где клиент может увидеть и протестировать линейку экранов/киосков. | K11: Telegram t.me/ctccapital — активен, посты почти ежедневно (последние \~10-12.09.2026): новинки оборудования, участие в выставке Light+Audio Tec 2026, семинары для образования, кейсы школьных инсталляций. YouTube и VK тоже есть. | L11: Поставщик / бенчмарк партнёрской программы | M11: C | N11: Запросить дилерские условия и сравнить с закупкой через Шанхай | O11: Проверено, данные изменены | P11: https://ctccapital.ru/ ; https://t.me/s/ctccapital
A12: ЛЕ-Интеграция | B12: Широкопрофильный | C12: leintegration.ru | D12: 7720820948 | E12: =INDEX(База!$E:$E,14) -> 2180 | F12: Москва | G12: ИТ-интегратор; AV/мультимедиа — одно из направлений (переговорные, видеостены, ситуационные центры) | H12: Видеостены, LED, ВКС, ситуационные центры, СКС, ИТ-инфраструктура | I12: Комплексный проект «под ключ»: аудит → проект → поставка → монтаж → сервис; тендеры 44/223-ФЗ | J12: Страница «Для интеграторов» на сайте: производство нестандартных корпусов, стоек, LED-конструкций и брендирования под их проекты (White Label) | K12: Не проверено — открыть сайт, найти иконки соцсетей, оценить частоту постов | L12: Заказчик субподряда / WL-производства | M12: B | N12: Выйти на руководителя AV-направления или закупки; предложить WL-производство нестандартных конструкций с гарантией до 5 лет | O12: Сайт не открывается (ошибка SSL-сертификата) | Q12: Сайт не открылся — проверить вручную или найти актуальный домен по ИНН; колонки G–K сейчас шаблонные, не факты
A13: ЦС Проект | B13: Интегратор АВ | C13: digis.ru | D13: 7709697296 | E13: =INDEX(База!$E:$E,15) -> 1991 | F13: Москва | G13: Крупнейший российский дистрибьютор профессионального AV-оборудования и мультимедийных решений для образования, бизнеса, Hi-Fi/CI; заявляет 70+ вендоров, 9500+ товаров, 3500+ партнёров. | H13: Дистрибуция AV-оборудования (проекторы, экраны, ЖК-панели, LED-экраны, акустика); интерактивные доски/дисплеи для образования; проектная интеграция «под ключ»; курсы учебного центра; сервисные центры. | I13: Партнёрская программа («Стать партнёром»); учебный центр с курсами для партнёров; акция — бесплатный кронштейн Peerless-AV при покупке проектора Exell (до 30.09). Цен «от» и % скидок нет на сайте. | J13: Перенять модель учебного центра DIGIS (регулярные бесплатные курсы/вебинары по продукту для партнёров) — вовлекать AV-интеграторов через обучение работе с оборудованием Simple Touch. | K13: Telegram t.me/digisgroup — активно, неск. постов/день (последние \~06.08): акции на оборудование, анонсы вебинаров, обзор шоурума, новинки брендов. VK vk.com/digisgroup и Rutube есть, содержание не проверено. | L13: Партнёр: покупатель LED / киосков / стендов под своим брендом (WL) | M13: B | N13: Звонок собственнику/коммерческому: WL-производство LED-экранов, киосков, корпусов под их бренд по дилерской цене | O13: Проверено 25.09.2026 | P13: https://digis.ru/ ; https://t.me/s/digisgroup | Q13: Это Digis — дистрибьютор, не WL-покупатель: Тип → «Дистрибьютор», роль → «Поставщик / бенчмарк партнёрки (учебный центр)»
A14: Astronis | B14: Широкопрофильный | C14: astronis.ru | D14: 7703402732 | E14: =INDEX(База!$E:$E,17) -> 1953 | F14: Москва | G14: Astronis — российский ИТ-интегратор (с 2015 г.): проектирование и внедрение мультимедийных, телеком- и вычислительных систем, унифицированных коммуникаций для организаций. | H14: Мультимедиа для переговорных/кабинетов руководителей, видеостены, ситуационные центры, медиафасады; телеком-сети; вычислительная инфраструктура/ЦОД; унифицированные коммуникации и телефония. | I14: Консалтинг и разработка ТЗ; поставка оборудования и ПО; монтаж и пусконаладка; техподдержка 24/7; обучение персонала. Цен, скидок, гарантии или акций с цифрами на сайте нет. | J14: Перенять модель полного цикла сервиса (консалтинг → поставка → монтаж → техподдержка 24/7 → обучение) как формат комплексного пакетного предложения для крупных заказчиков Simple Touch. | K14: Соцсетей на сайте нет. | L14: Заказчик субподряда / WL-производства | M14: B | N14: Выйти на руководителя AV-направления или закупки; предложить WL-производство нестандартных конструкций с гарантией до 5 лет | O14: Проверено 25.09.2026 | P14: https://astronis.ru/
A15: Оберон | B15: Широкопрофильный | C15: oberon-it.ru | D15: 7722283103 | E15: =INDEX(База!$E:$E,18) -> 1856 | F15: Москва | G15: Oberon — российский ИТ-интегратор с 2003 г., «экосистема цифровизации бизнеса»: инженерная инфраструктура, ЦОД, телеком, мультимедиа, ИБ, сервис. | H15: Мультимедийные решения (одно из направлений), инженерная инфраструктура зданий, создание/реконструкция ЦОД, телеком-решения, информационная безопасность, сервис и аутсорсинг. | I15: Круглосуточный сервисный центр (24/7). Цен «от», скидок, гарантии с цифрами или акций на сайте нет. | J15: Перенять позиционирование «сервисный центр 24/7» — предлагать гарантированную круглосуточную поддержку как часть пакета для крупных инсталляций Simple Touch. | K15: Соцсетей на сайте нет. | L15: Заказчик субподряда / WL-производства | M15: B | N15: Выйти на руководителя AV-направления или закупки; предложить WL-производство нестандартных конструкций с гарантией до 5 лет | O15: Проверено 25.09.2026 | P15: https://oberon-it.ru/
A16: Труконф | B16: Вендор | C16: trueconf.ru | D16: 9717098324 | E16: =INDEX(База!$E:$E,19) -> 1832 | F16: Москва | G16: Труконф — российский вендор ВКС-платформы и корпоративного мессенджера (звонки, чаты, конференции до 2000 участников) для бизнеса и госсектора; акцент на импортонезависимость. | H16: TrueConf Server Free/Server/Enterprise, корпоративный мессенджер, TrueConf Group/Room (терминалы), TrueConf Coordinator, мобильные и десктоп-приложения | I16: TrueConf Server Free — бесплатно до 300 польз., UltraHD-конференции до 10 участников; бесплатная миграция с Telegram; пробная версия по запросу; демо для Enterprise по записи. Точные цены на сайте не опубликованы (раздел «Цены» — по запросу). | J16: Freemium-заход: бесплатный базовый продукт как лид-магнит с апсейлом на платный тариф — применить для лидогенерации (бесплатный демо-пакет/калькулятор на сайте Simple Touch) | K16: Telegram t.me/true\_trueconf — \~1-2 поста/день, последний 13.09.2026: road-show/демо-туры, продуктовые фичи, выставки (LEAP, InfoComm India). Есть VK vk.com/trueconf\_club и RuTube — не детализировано (VK заблокирован для проверки) | L16: Технологический партнёр | M16: A | N16: Подать заявку в партнёрскую программу TrueConf на этой неделе | O16: Проверено 25.09.2026 | P16: https://trueconf.ru/ ; https://t.me/s/true\_trueconf | Q16: Открыть VK/Telegram вручную: дата последнего поста, частота, 2–3 темы
A17: Vkorpe | B17: Широкопрофильный | C17: vkorpe.ru | D17: 7810341266 | E17: =INDEX(База!$E:$E,20) -> 1575 | F17: Санкт-Петербург | G17: Vkorpe — российский системный интегратор (СПб/Москва, 10 лет на рынке): проектирование и внедрение ИТ-решений, автоматизация бизнеса, работа с госконтрактами. | H17: Поставка ИТ-инфраструктуры и оборудования; разработка и внедрение ПО (в т.ч. импортозамещение); аудит сетевой безопасности; развёртывание Wi-Fi и радиообследование; решения для переговорных, аудиторий, складов, производств, ритейла, образования. | I17: Конкретных цен «от», скидок, гарантии или акций на сайте нет. | J17: Явной применимой идеи с сайта нет; заявленный масштаб (1000+ госконтрактов, 4000+ клиентов, 54 партнёра) интересен как потенциальный партнёрский канал, а не как техника для копирования. | K17: VK vk.com/vkorpe — содержание не проверено (VK не открывается инструментом проверки). | L17: Заказчик субподряда / WL-производства | M17: B | N17: Выйти на руководителя AV-направления или закупки; предложить WL-производство нестандартных конструкций с гарантией до 5 лет | O17: Проверено 25.09.2026
A18: АБАК-2000 | B18: Широкопрофильный | C18: abak2000.ru | D18: 3445084000 | E18: =INDEX(База!$E:$E,21) -> 1355 | F18: Москва | G18: АБАК-2000 — федеральный системный интегратор (Москва/Волгоград): создание, развитие и обслуживание ИТ-инфраструктуры предприятий. | H18: ИТ-инфраструктура (сети, виртуализация, облака, Wi-Fi); комплексные системы безопасности (видеонаблюдение, СКУД, досмотр); АСУ ТП; информационная безопасность; АВ и конференц-решения (видеостены, ситуационные центры); ЦОД; собственные продукты (CowWatch и др.). | I18: Конкретных цен «от», скидок, гарантии или акций на сайте нет. | J18: Нет прямой применимой идеи для продукта; можно перенять формат регулярных кейс-постов в Telegram (истории внедрений с цифрами эффекта) для продвижения Simple Touch. | K18: Telegram @abak2000 — последние найденные посты датированы январём 2026, примерно раз в 1-2 дня: сертификации сотрудников, интервью руководства, агротех-кейсы, проекты по инфраструктуре и безопасности. VK, Rutube, Dzen тоже есть, не детализированы. | L18: Заказчик субподряда / WL-производства | M18: B | N18: Выйти на руководителя AV-направления или закупки; предложить WL-производство нестандартных конструкций с гарантией до 5 лет | O18: Проверено 25.09.2026 | P18: https://abak2000.ru/ ; https://t.me/s/abak2000
A19: ИЦ Телеком-Сервис | B19: Широкопрофильный | C19: teleserv.ru | D19: 7736038341 | E19: =INDEX(База!$E:$E,22) -> 1340 | F19: Москва | G19: ИЦ Телеком-Сервис — российский ИТ-интегратор («искусство интеграции»): проектирование, внедрение и обслуживание комплексных ИТ-систем. | H19: Инженерная инфраструктура (СКС, охлаждение, ИБП); сетевая инфраструктура и виртуализация; АВ и мультимедиа (переговорные, видеостены, диспетчерские); техническая и информационная безопасность (СКУД, видеонаблюдение); унифицированные коммуникации; обслуживание ИТ-инфраструктуры. | I19: Кнопка «Заявка на проект»; типы сервисных пакетов упоминаются без деталей. Цен «от», скидок, гарантии или акций с цифрами на сайте нет. | J19: Перенять формат кейс-постов в Telegram с конкретными реализованными АВ-проектами (например, оснащение отеля) — публиковать похожие истории внедрений Simple Touch. | K19: Telegram t.me/ic\_telecom\_service — активен, регулярные посты: импортозамещение (Astra Linux, RED OS), партнёрства (Ideco NGFW), кейсы АВ-проектов (например, отель «Эрбелия от Васта»). VK в футере есть, не детализирован. | L19: Заказчик субподряда / WL-производства | M19: B | N19: Выйти на руководителя AV-направления или закупки; предложить WL-производство нестандартных конструкций с гарантией до 5 лет | O19: Проверено 25.09.2026 | P19: https://teleserv.ru/ ; https://t.me/s/ic\_telecom\_service
A20: Profdisplay | B20: Дистрибьютор | C20: profdisplays.ru | D20: 9715207761 | E20: =INDEX(База!$E:$E,23) -> 1263 | F20: Москва | G20: PROFDISPLAY — московский дистрибьютор профессионального AV-оборудования: дисплеи, LED-решения, звук, коммутация. | H20: Информационные LCD/LED-дисплеи, интерактивные панели, видеостены, LED-экраны и модули, акустика/усилители/микшеры, оборудование коммутации и передачи сигнала (удлинители, масштабаторы). | I20: Рекомендованная розничная цена на товарах; прайс-лист для партнёров; акция — бесплатный сплит-кондиционер при заказе кабинетного LED от 2 000 000 ₽ (до 30.09.2026). | J20: Перенять акцию «подарок к крупному заказу» (аналог бесплатного кондиционера у Profdisplay) — например, бесплатная доставка/монтаж или доп. оборудование при заказе экрана/киоска Simple Touch от определённой суммы. | K20: Telegram t.me/profdisplays — активен, посты несколько раз в неделю (последние \~конец июля): поступления оборудования (BOE, Hisense), кейсы инсталляций, отраслевые события (InfoComm Asia, ЧМ по футболу/Hisense VAR). | L20: Поставщик + конкурент в интерактивных панелях | M20: B | N20: Запросить дилерские условия и сравнить с закупкой через Шанхай | O20: Проверено, данные изменены | P20: https://profdisplays.ru/ ; https://t.me/s/profdisplays
A21: ASCREEN | B21: Музей, развлечения | C21: ascreen.ru | D21: 7804472253 | E21: =INDEX(База!$E:$E,24) -> 1052 | F21: Санкт-Петербург | G21: Ascreen — компания мультимедийных решений на стыке креатива и AV/архитектурных технологий: музейные и корпоративные экспозиции, выставочные стенды, интерьеры; на рынке более 25 лет. | H21: АВ-интеграция, музейные и корпоративные экспозиции, выставочные стенды, мультимедийные инсталляции, дизайн бизнес-пространств, архитектурно-инженерные решения | I21: Нет на сайте: цены, скидки, гарантии, акции, партнёрская программа не опубликованы — предложение только индивидуально через менеджера | J21: У Ascreen нет открытых цен/акций — выигрышный ход для Simple Touch: публиковать цены «от» на типовые интерактивные продукты, чего у конкурента нет | K21: Telegram t.me/ascreengroup — \~1-2 поста/неделю, последний 08.04.2026 (давно не обновлялся): кейсы и портфолио музейных проектов, отраслевые события, премии (ProIntegration Awards). Также VK vk.com/ascreen и RuTube — не детализировано | L21: Прямой конкурент (интерактив) | M21: A (мониторинг) | N21: Тайный покупатель: КП на сенсорный стол и киоск для музея | O21: Проверено, данные изменены | P21: https://ascreen.ru/ ; https://t.me/s/ascreengroup | Q21: Открыть VK/Telegram вручную: дата последнего поста, частота, 2–3 темы
A22: ГИГАНТ | B22: Широкопрофильный | C22: gigant.ru | D22: 7720768984 | E22: =INDEX(База!$E:$E,25) -> 943 | F22: Москва | G22: ГИГАНТ — российский ИТ-интегратор (15 лет на рынке, 180+ инженеров, 3000+ проектов): комплексные ИТ- и мультимедийные решения «под ключ». | H22: Инженерная инфраструктура ЦОД; мультимедиа (ВКС, АВ-системы, интерактивные дисплеи); печатная техника (МФУ); корпоративное ПО и облака; клиентские устройства; ИТ-аутсорсинг и кибербезопасность; серверы/виртуализация/сети. | I22: Распродажа «сотни товаров по спецценам» (до 31.10); партнёрство с 250+ производителями оборудования и ПО; решения «под ключ». Конкретных цен «от» или % скидок не указано. | J22: Перенять идею сезонной распродажи «сотни товаров по спецценам» с ограниченным сроком — периодические акции на складские остатки экранов/киосков Simple Touch. | K22: Telegram t.me/gigant\_computer\_systems — низкая частота (последние посты \~осень 2025, примерно раз в 2-4 недели): рейтинги (CNews500, TAdviser500), темы ИИ/данных, юбилей компании, отечественное железо. VK, Rutube, Dzen тоже есть, не детализированы. | L22: Заказчик субподряда / WL-производства | M22: B | N22: Выйти на руководителя AV-направления или закупки; предложить WL-производство нестандартных конструкций с гарантией до 5 лет | O22: Проверено 25.09.2026 | P22: https://gigant.ru/ ; https://t.me/s/gigant\_computer\_systems
A23: Хайтэк-Интеграция | B23: Широкопрофильный | C23: hi-tech.org | D23: 7722350688 | E23: =INDEX(База!$E:$E,26) -> 818 | F23: Москва | G23: Хайтэк-Интеграция — московский системный интегратор: комплексные услуги цифровой трансформации для организаций. | H23: ИТ-инфраструктура; решения Индустрии 4.0 (IIoT); контакт-центры; сети и телеком; информационная безопасность; мультимедиа (АВ-системы, ВКС); инженерные и технические системы безопасности. | I23: Прайс-лист доступен по ссылке на Яндекс.Диск (условия не видны); активная партнёрская программа (упомянуты партнёрства с BFG Group, Wellink НТЦ и др.), детали не раскрыты. Цен «от», скидок или гарантии с цифрами на сайте нет. | J23: Нет явной применимой идеи с сайта — можно отметить открытость к анонсам новых партнёрств в публичном поле как формат для Simple Touch. | K23: Соцсетей на сайте нет. | L23: Заказчик субподряда / WL-производства | M23: B | N23: Выйти на руководителя AV-направления или закупки; предложить WL-производство нестандартных конструкций с гарантией до 5 лет | O23: Проверено 25.09.2026 | P23: https://hi-tech.org/
A24: Видау Системс | B24: Бродкаст | C24: vidau.tv | D24: 7733852150 | E24: =INDEX(База!$E:$E,27) -> 797 | F24: Москва | G24: Оборудование и интеграция для ТВ, студий и видеопроизводства | H24: Студийное, вещательное и видеооборудование | I24: Оснащение студий под ключ | J24: Не приоритет; как идея — «студия для корпоративного видео» в линейке ВКС | K24: Не проверено — открыть сайт, найти иконки соцсетей, оценить частоту постов | L24: Низкая релевантность | M24: C | N24: Не тратить время сейчас | O24: Сайт не открывается (соединение не устанавливается — проверено через WebFetch и браузер) | Q24: Сайт не открылся — проверить вручную или найти актуальный домен по ИНН; колонки G–K сейчас шаблонные, не факты
A25: Джаз Телеком | B25: Дистрибьютор | C25: voip-shop.ru | D25: 7722321623 | E25: =INDEX(База!$E:$E,29) -> 793 | F25: Москва | G25: Джаз Телеком (VoIP Shop) — российский поставщик телеком- и IP-оборудования: связь, ВКС, конференц-системы, дисплеи. | H25: IP-телефоны, IP-АТС; оборудование ВКС (терминалы, серверы, камеры); конференц-системы (микрофоны, аудиопроцессоры); дисплейные системы (интерактивные панели, видеостены, проекторы); коммутация AV-сигнала; гарнитуры; GSM-шлюзы; сетевое оборудование. | I25: Розничные цены на отдельные товары указаны (например, гарнитуры Jabra \~39-60 тыс. ₽); пакетных предложений, скидок, гарантии или акций не найдено. | J25: Нет на сайте — явной применимой идеи не найдено. | K25: Соцсетей на сайте нет. | L25: Поставщик ВКС | M25: C | N25: Запросить дилерские условия и сравнить с закупкой через Шанхай | O25: Проверено, данные изменены | P25: https://voip-shop.ru/
A26: ЭЙЧДИ | B26: Светодиодка | C26: hdlt.ru | D26: 7724865932 | E26: =INDEX(База!$E:$E,30) -> 771 | F26: Москва | G26: HD LED Tech (ЭЙЧДИ) — производитель светодиодных экранов: «изготовление, продажа и установка светодиодных экранов в России и СНГ», позиционирует себя как продавец «по низким ценам от производителя». | H26: Медиафасады, уличные видеоэкраны, экраны для помещений, прозрачные экраны, COB/GOB-экраны, гибкие видеоэкраны | I26: Нет на сайте: точных цен «от» и % скидок нет; есть акции без цифр («Осенний ценопад», «2 недели суперцен»); расчёт стоимости только по заявке. Партнёрская программа для дилеров на сайте не представлена | J26: Публиковать открытую цену за м² на ходовые LED-модели (у HDLT цены закрыты даже в акциях) — конкурентное преимущество Simple Touch в прозрачности КП | K26: Telegram t.me/hdlt\_ru — активный, \~1-2 поста/день: технические характеристики экранов, командная работа/производство, кейсы медиафасадов. Также VK vk.com/hd\_led\_tech, RuTube, Дзен dzen.ru/hdlt — не детализировано | L26: Прямой конкурент №1 в LED (Москва, своё производство) | M26: A (мониторинг) | N26: Тайный покупатель: запросить КП на экран 3×2 м indoor и 6×3 м outdoor — сравнить цену, сроки, гарантию, подачу КП | O26: Проверено 25.09.2026 | P26: https://hdlt.ru/ ; https://t.me/s/hdlt\_ru | Q26: На сайте цен нет (цены видны только в карточке на Яндекс Картах) — перепроверить и держать в бенчмарке
A27: ТЕХНОМЕДИА ГРУПП | B27: Интегратор АВ | C27: tmgroup.ru | D27: 6143088075 | E27: =INDEX(База!$E:$E,31) -> 767 | G27: Техномедиа Групп — российский системный интегратор аудиовизуальных комплексов и мультимедийных решений для крупного бизнеса. | H27: Технический аудит и бюджетирование, проектирование АВ-систем, монтаж, эксплуатация и техподдержка, диспетчерские/ситуационные центры, переговорные и конференц-залы | I27: Нет на сайте: цены, скидки, сроки гарантии, стоимость выезда/демо не опубликованы — только форма консультации | J27: Нет соцсетей и открытых офферов — предложить бенчмарк: у Simple Touch фикс-цены и сроки на типовые пакеты «переговорная S/M/L», это выделит на их фоне | K27: Соцсетей на сайте нет | L27: Партнёр: покупатель LED / киосков / стендов под своим брендом (WL) | M27: A | N27: Региональный партнёр/дилер: WL-производство + дилерская цена | O27: Проверено 25.09.2026 | P27: https://tmgroup.ru/
A28: Д2 Групп | B28: Интегратор АВ | C28: d2group.ru | D28: 7707661897 | E28: =INDEX(База!$E:$E,32) -> 719 | F28: Москва | G28: Д2 Групп — «динамично развивающаяся группа компаний, одна из ведущих российских в области комплексных AV-решений и IT-проектов»: интегратор и поставщик оборудования. | H28: AV-оборудование (проекторы, видеопроцессоры, акустика, LCD/LED-панели), IT-оборудование и СХД, конференц-залы и ситуационные центры, ВКС, сервис и аренда оборудования | I28: Нет на сайте: цены «от», скидки, гарантия, бесплатный демо не опубликованы. Есть раздел «Партнёры» (d2group.ru/company/partners), но без конкретных условий — только список 40+ брендов-поставщиков | J28: У Д2 партнёрский раздел есть, но без конкретики — показать выгодное отличие: у Simple Touch прозрачные условия WL-производства и дилерские цены сразу на сайте | K28: Соцсетей на сайте нет | L28: Партнёр: покупатель LED / киосков / стендов под своим брендом (WL) | M28: A | N28: Звонок собственнику/коммерческому: WL-производство LED-экранов, киосков, корпусов под их бренд по дилерской цене | O28: Проверено 25.09.2026 | P28: https://d2group.ru/ ; https://d2group.ru/company/partners
A29: Visuals | B29: Музей, развлечения | C29: visuals.ru | D29: 7730700872 | E29: =INDEX(База!$E:$E,33) -> 709 | F29: Москва | G29: Visuals — студия мультимедийных решений для музеев, выставок и развлекательных пространств: «комплексная реализация проектов, в которых мультимедиа играет ключевую роль». | H29: Интерактивные музеи и выставочные стенды, VR/AR-приложения, мультимедийные парки развлечений, 3D-видеомэппинг и LED-инсталляции, шоурумы и корпоративные музеи | I29: Нет на сайте: цены, гарантии, демо не опубликованы — предложение только через форму «Обсудить проект» или презентацию | J29: Сильное портфолио (Музей русского импрессионизма, музей оружия в Туле, выставка «Пётр I», Транснефть) без открытых цен — предложить связку: они контент/концепция, Simple Touch — производство корпусов/киосков/LED под их проекты | K29: YouTube youtube.com/channel/UC920C01Popu3yBd72B8MZ0g (активность не детализирована), также Vimeo vimeo.com/user12144796 и Behance behance.net/visuals\_. Telegram/VK/Дзен/Rutube на сайте не найдены | L29: Конкурент в музеях + партнёр (у них контент, у нас производство) | M29: A | N29: Предложить связку: они — концепция и контент, Simple Touch — корпуса, киоски, LED, МАФ, стенды | O29: Проверено 25.09.2026 | P29: https://visuals.ru/ | Q29: Открыть VK/Telegram вручную: дата последнего поста, частота, 2–3 темы
A30: П10 | B30: Светодиодка | C30: p10.ru | D30: 7723917306 | E30: =INDEX(База!$E:$E,34) -> 703 | F30: Москва | G30: П10 (P10.RU) — дистрибьютор комплектующих для LED-экранов с прямым импортом из Китая; более 10 лет на рынке, также продаёт готовые экраны и оказывает сервис/ремонт. | H30: LED-модули, видеопроцессоры/контроллеры (Novastar, Colorlight, Huidu, Linsn, VDWALL), блоки питания, алюминиевые кабинеты, готовые экраны (indoor/outdoor/прозрачные/прокатные), сервис-центр | I30: Более 3 млн позиций на складе в Москве, доставка в день заказа, самовывоз. Точных цен «от» за м², сроков гарантии, рассрочки/лизинга и калькулятора стоимости на сайте не найдено | J30: У П10 нет калькулятора цены — Simple Touch может выигрывать наглядным онлайн-калькулятором стоимости экрана как инструментом лидогенерации | K30: Соцсетей на сайте нет (только сторонняя ссылка на видео Rutube, не официальный канал) | L30: Прямой конкурент | M30: A (мониторинг) | N30: Тайный покупатель: запросить КП на экран 3×2 м indoor и 6×3 м outdoor — сравнить цену, сроки, гарантию, подачу КП | O30: Проверено, данные изменены | P30: https://p10.ru/
A31: Анкомп | B31: Интегратор АВ | C31: ancomp.ru | D31: 7717103901 | E31: =INDEX(База!$E:$E,35) -> 696 | F31: Москва | G31: Ancomp — производитель мультимедийного и IT-оборудования и системный интегратор: оснащение «под ключ» переговорных, образовательных и офисных пространств. | H31: Интерактивные панели (собственная линейка AnTouch), LED-экраны (indoor/outdoor/прокат), ВКС и системы управления, проекционное и световое оборудование, компьютерная техника, серверы/СХД | I31: На сайте: чёткое соблюдение гарантийных обязательств, гибкие условия постгарантийного обслуживания, 10 000+ единиц техники/год, 50+ AV/IT-проектов/год, 60+ сертифицированных специалистов. Точных цен, % скидок, сроков гарантии не опубликовано | J31: У Ancomp своя линейка интерактивных панелей (AnTouch) — прямая конкуренция в интерактиве; стоит следить за их продуктовыми анонсами в Telegram и сравнивать цены | K31: Telegram t.me/ancomp\_official — активный, \~2-3 поста/неделю, последний 06.08.2026: новинки оборудования (AnTouch G4, моноблоки), решения для образования, отраслевая аналитика. Также VK vk.com/ancompru, YouTube, Дзен dzen.ru/ancomp | L31: Конкурент в ВКС и интерактивных панелях + потенциальный WL-партнёр | M31: A (мониторинг) | N31: Тайный покупатель: КП на переговорную на 12 мест с ВКС + запросить цену на интерактивную панель AnTouch | O31: Проверено, данные изменены | P31: https://ancomp.ru/ ; https://t.me/s/ancomp\_official
A32: Видео ЛЕНД | B32: Прокат/Эвенты | C32: videoland-pro.ru | D32: 7701704424 | E32: =INDEX(База!$E:$E,36) -> 678 | F32: Москва | G32: Прокат и техническое обеспечение мероприятий | H32: LED-экраны, проекция, звук, свет в аренду | I32: Аренда с монтажом и техподдержкой на площадке | J32: Опция «аренда LED с выкупом» для клиентов, которые не готовы платить сразу | K32: Не проверено — открыть сайт, найти иконки соцсетей, оценить частоту постов | L32: Покупатель LED-экранов / кейс-партнёр | M32: B | N32: Предложить поставку прокатных LED-кабинетов с завода в Шанхае | O32: Сайт не открывается (таймаут соединения / DNS, проверено через WebFetch и браузер) | Q32: Сайт не открылся — проверить вручную или найти актуальный домен по ИНН; колонки G–K сейчас шаблонные, не факты
A33: ДИЛ | B33: Интегратор АВ | C33: dil-it.ru | D33: 7710892703 | E33: =INDEX(База!$E:$E,37) -> 656 | F33: Москва | G33: ООО «ДИЛ» — ИТ-компания (Екатеринбург) с 20+ лет опыта: проектирование, поставка, внедрение и обслуживание систем автоматизации бизнеса, включая AV-интеграцию. | H33: AV-интеграция для переговорных/залов принятия решений/обучения, IT-безопасность, аудиты инфраструктуры, сетевые решения, отказоустойчивая ИТ-инфраструктура | I33: Нет на сайте: цены, скидки, гарантия, бесплатный выезд/демо, партнёрская программа не опубликованы | J33: Нет соцсетей и открытых офферов — предложить типовой пакет «переговорная S/M/L» с фикс-ценой как понятную точку входа для региона | K33: Соцсетей на сайте нет | L33: Партнёр: покупатель LED / киосков / стендов под своим брендом (WL) | M33: A | N33: Звонок собственнику/коммерческому: WL-производство LED-экранов, киосков, корпусов под их бренд по дилерской цене | O33: Проверено, данные изменены | P33: https://dil-it.ru/
A34: ГК Спутник | B34: Широкопрофильный | C34: gksputnik.ru | D34: 7724418010 | E34: =INDEX(База!$E:$E,38) -> 651 | F34: Москва | G34: ГК Спутник — московский интегратор: разработка и внедрение корпоративных решений и инженерных систем «под ключ». | H34: Инфраструктурные решения (доступность, надёжность, безопасность); мультимедийные решения (дизайн, архитектура «умных» объектов); информационная безопасность; заказная разработка ПО. | I34: Конкретных цен «от», скидок, гарантии или акций на сайте нет. | J34: Нет на сайте — явной применимой идеи не найдено. | K34: Соцсетей на сайте нет. | L34: Заказчик субподряда / WL-производства | M34: B | N34: Выйти на руководителя AV-направления или закупки; предложить WL-производство нестандартных конструкций с гарантией до 5 лет | O34: Проверено 25.09.2026 | P34: https://gksputnik.ru/
A35: ПК Аллегри | B35: Вендор | C35: allegri-group.ru | D35: 7724413781 | E35: =INDEX(База!$E:$E,39) -> 645 | F35: Москва | G35: ПК Аллегри — производитель кастомных крепёжных и конструктивных решений для профессионального мультимедиа/АВ-оборудования (Подольск). | H35: Каркасы LED-экранов и видеостен, кронштейны для ТВ/ЖК-панелей, телеком-стойки и шкафы, моторизованные крепления, стойки для ВКС, крепления для акустики и проекторов, подставки для интерактивных панелей, flight-кейсы, мебель под заказ. | I35: Изготовление от 1 дня; работа по чертежам заказчика; инженерное проектирование; бесплатные консультации. Цен «от», скидок или гарантии с цифрами на сайте нет. | J35: Потенциальный поставщик кастомных креплений/стоек для экранов и киосков Simple Touch — рассмотреть как субподрядчика по механическим конструкциям вместо собственного производства крепежа. | K35: Telegram t.me/allegri\_group — низкая частота (последние посты \~февраль 2026): участие в выставке ARTDOM, дизайнерские инсталляции с LED и мультимедиа (SENSE SENSORY, BETTE & SPLENDY). | L35: Потенциальный технологический партнёр | M35: B | N35: Изучить партнёрские условия на сайте | O35: Проверено 25.09.2026 | P35: https://allegri-group.ru/ ; https://t.me/s/allegri\_group
A36: ICL SERVICES | B36: Широкопрофильный | C36: icl-services.com | D36: 7728897484 | E36: =INDEX(База!$E:$E,40) -> 620 | F36: Москва | G36: ICL Services — крупный российский ИТ-интегратор (20 лет): полный цикл цифровых решений от аудита до внедрения и поддержки. | H36: Информационная безопасность (аудит, пентесты, SOC 24/7, DLP); заказная разработка (RPA, BI); ИИ (computer vision, LLM-агенты); интеграция инфраструктуры и облака; ИТ-аутсорсинг; инженерный центр (ЦОД); поставка оборудования; продукты Kolibri-ARM, AISee и др. | I36: DLP-аутсорсинг «0 рублей на старте» с бесплатным 30-дневным тестом; бесплатный аудит 1С (14 дней); бесплатная ИИ-диагностика готовности (до 30.09.2026); бесплатное тестирование Kolibri-ARM (экономия до 87% трудозатрат); ПАК EVO Lite от 98 600 ₽. | J36: Перенять модель «бесплатный тест/аудит с ограниченным сроком + конкретная цифра экономии» — например, бесплатная диагностика цифровой инфраструктуры клиента с расчётом потенциальной выгоды от внедрения решений Simple Touch. | K36: Telegram t.me/ICL\_Services — активен, частые посты (последние \~24.09.2026): участие в отраслевых форумах (ритейл, ИТОПК), темы ИИ на рынке РФ, ИТ-инфраструктура (SD-WAN). Также VK, Dzen, Rutube, YouTube, LinkedIn. | L36: Низкая релевантность | M36: C | N36: Не тратить время сейчас | O36: Проверено, данные изменены | P36: https://icl-services.com/ ; https://t.me/s/ICL\_Services
A37: Лемьер | B37: Интегратор АВ | C37: lemier.ru | D37: 7720715213 | E37: =INDEX(База!$E:$E,41) -> 618 | F37: Москва | G37: Lemier — «решения для людей и бизнеса»: комплексные IT-инфраструктура, аудиовизуальные и инженерные решения, «умный офис» под ключ. | H37: IT-инфраструктура, аудиовизуальные решения, инженерные решения, «умный офис», дизайн-услуги, сервисное обслуживание | I37: Нет на сайте: цены, скидки, гарантия, бесплатный выезд/демо, партнёрская программа не опубликованы | J37: Нет соцсетей и открытых офферов — предложить типовой пакет «переговорная S/M/L» с фикс-ценой и сроком как понятную точку входа | K37: Соцсетей на сайте нет | L37: Партнёр: покупатель LED / киосков / стендов под своим брендом (WL) | M37: A | N37: Звонок собственнику/коммерческому: WL-производство LED-экранов, киосков, корпусов под их бренд по дилерской цене | O37: Проверено 25.09.2026 | P37: https://lemier.ru/
A38: Брюллов Консалтинг | B38: Дистрибьютор | C38: brullov.com | D38: 7729443187 | E38: =INDEX(База!$E:$E,42) -> 604 | F38: Москва | G38: Брюллов Консалтинг — поставщик и разработчик мультимедийных решений (с 2006 г.): оснащение переговорных и профессиональных пространств АВ-оборудованием. | H38: Конференц-системы и синхронный перевод; микрофоны/радиосистемы; звукоусиление; BYOD-коллаборация; конференц-камеры; видеокоммутация; дисплейные системы; запись/стриминг; системы управления; digital signage/IPTV; бренды RMS, Televic, Fohhn и др. | I38: Прайс-лист и каталог для скачивания; онлайн-конфигуратор для самостоятельного проектирования системы; заказ проекта под ключ; гарантия и возврат (детали на странице поддержки). | J38: Перенять идею онлайн-конфигуратора для самостоятельного подбора комплектации — сделать похожий инструмент для конфигурации интерактивных панелей/киосков Simple Touch под задачи клиента. | K38: VK vk.com/BrullovConsulting, Rutube rutube.ru/channel/25551303 — содержание не проверено детально. | L38: Поставщик / бенчмарк партнёрской программы | M38: C | N38: Запросить дилерские условия и сравнить с закупкой через Шанхай | O38: Проверено, данные изменены | P38: https://brullov.com/
A39: Электронные Системы | B39: Светодиодка | C39: gtlamp.ru | D39: 4205176605 | E39: =INDEX(База!$E:$E,45) -> 580 | G39: GTLight (Электронные Системы, gtlamp.ru) — производитель LED-экранов и медиафасадов с собственным производством в РФ; работает с 1999 г., более 37 000 реализованных проектов. | H39: Медиафасады (реечные/модульные/сетчатые/прозрачные), уличные LED-экраны (билборды, бегущие строки), интерьерные экраны для залов/сцен/ритейла, спортивные табло и видеокубы, монтаж, аренда экранов | I39: Цены от 14 000₽ (бегущая строка), от 47 000₽/м² (медиафасады), от 65 000₽/м² (уличные экраны); гарантия 1-5 лет в зависимости от оборудования; производство от 7 дней (300 м²/неделю); интерактивный калькулятор стоимости на сайте | J39: У GTLight открытые цены за м² и онлайн-калькулятор с вводом размеров — сильный бенчмарк: Simple Touch стоит внедрить аналогичный калькулятор с ценой «от» на сайте | K39: Telegram t.me/gtlamp\_ru — НЕ активен, последний пост 11.11.2024 (почти 2 года назад): экраны для школ/колледжей, госучреждений, технические характеристики. Также VK, YouTube, Дзен, RuTube — не детализированы | L39: Прямой конкурент | M39: A (мониторинг) | N39: Тайный покупатель: запросить КП на экран 3×2 м indoor и 6×3 м outdoor — сравнить цену, сроки, гарантию, подачу КП | O39: Проверено, данные изменены | P39: https://gtlamp.ru/ ; https://t.me/s/gtlamp\_ru | Q39: Открыть VK/Telegram вручную: дата последнего поста, частота, 2–3 темы
A40: Future Vision | B40: Светодиодка | C40: future-vision.ru | D40: 6658436206 | E40: =INDEX(База!$E:$E,46) -> 545 | F40: Екатеринбург | G40: Future Vision (ООО «Компэлс Интеграция») — производитель LED-экранов и медиафасадов с собственным заводом (Екатеринбург/Москва), работает по всей РФ; экраны включены в реестр Минпромторга (СТ-1). | H40: Медиафасады, уличные экраны, экраны для сцены/кинотеатров/стадионов/ТРЦ/конференц-залов, прозрачные и гибкие экраны, 3D-экраны, видеокубы, текстурные экраны | I40: Индивидуальный подход, «гибкая система скидок», расширенная гарантия и сервис от производителя, бесплатная консультация; онлайн-калькулятор цены по типу/размеру/шагу пикселя. Точных цифр цен «от» на сайте не указано | J40: У Future Vision — полноценный личный кабинет дилера (логин/регистрация на сайте) с реестром Минпромторга как аргумент для гостендеров — Simple Touch стоит рассмотреть отдельный дилерский портал и статус в реестре Минпромторга | K40: Telegram @futurevisionled, VK и YouTube в подвале сайта — содержание не детализировано (не проверено вручную) | L40: Прямой конкурент | M40: A (мониторинг) | N40: Тайный покупатель: запросить КП на экран 3×2 м indoor и 6×3 м outdoor — сравнить цену, сроки, гарантию, подачу КП | O40: Проверено, данные изменены | P40: https://future-vision.ru/ ; https://future-vision.ru/dealers/ | Q40: Открыть VK/Telegram вручную: дата последнего поста, частота, 2–3 темы
A41: ОПЕН ВИЖН | B41: Широкопрофильный | C41: open-vision.ru | D41: 7726627740 | E41: =INDEX(База!$E:$E,47) -> 544 | F41: Москва | G41: Open Vision — московский системный интегратор: поставка ИТ-оборудования, комплексные инфраструктурные проекты, техподдержка по всей России. | H41: Унифицированные коммуникации и ВКС; серверные решения (виртуализация, облака, ЦОД); телемедицина; АВ и мультимедиа; внедрение бизнес-ПО; информационная безопасность; LED-экраны и видеостены; СХД; межсетевые экраны/защита от DDoS. | I41: Бесплатное 30-дневное тестирование сервера ВКС Vinteo; спецусловия на серверы из реестра Минпромторга (доставка 3-7 дней); скидка при полном заполнении формы заявки; безналичная оплата. | J41: Перенять идею бесплатного 30-дневного тест-драйва оборудования (по аналогии с Vinteo) — предлагать пробную установку интерактивной панели/киоска Simple Touch на 30 дней перед покупкой. | K41: VK и Twitter указаны, ссылки/содержание не проверены детально. Telegram/YouTube/Dzen/Rutube на сайте нет. | L41: Заказчик субподряда / WL-производства | M41: B | N41: Выйти на руководителя AV-направления или закупки; предложить WL-производство нестандартных конструкций с гарантией до 5 лет | O41: Проверено, данные изменены | P41: https://open-vision.ru/
A42: ВИНТЕО | B42: Вендор | C42: vinteo.ru | D42: 2312200249 | E42: =INDEX(База!$E:$E,48) -> 535 | G42: VINTEO — российский разработчик премиум-решений для видеоконференцсвязи (ВКС), on-premise серверы, \>12 лет разработок, 500+ проектов. | H42: Сервер ВКС VINTEO (стандарт Telepresence); клиенты Windows/macOS/Linux/Android/iOS/браузер; сценарии импортозамещения и миграции с иностранных ВКС; сенсорная панель управления видеотерминалами. | I42: Бесплатное пилотное тестирование (разворачивают за несколько часов); поддержка 24/7; гибкая лицензионная политика; партнёрская программа (60+ партнёров, «Стать партнёром»). Цен «от» и % скидок нет. | J42: Перенять модель бесплатного пилотирования с быстрым развёртыванием («за несколько часов, под контролем инженеров») — предлагать быструю бесплатную демо-установку экрана/киоска Simple Touch у клиента на объекте. | K42: Telegram t.me/vinteoru — активен, посты неск. раз/неделю (последние \~13.09.2026): релизы версий ПО, представление сотрудников, темы ИИ в ВКС. Также VK, Rutube, MAX в футере — не детализированы. | L42: Технологический партнёр | M42: B | N42: Изучить партнёрские условия на сайте | O42: Проверено, данные изменены | P42: https://vinteo.ru/ ; https://t.me/s/vinteoru
A43: Пилот | B43: Прочее | C43: www.pilot.ru | D43: 7726527350 | E43: =INDEX(База!$E:$E,50) -> 517 | F43: Москва | G43: Пилот — московский интегратор автоматизации розницы (с 1992 г.): ПО и оборудование для магазинов и торговых сетей. | H43: ПО Profi-T (кассовое), CodeMark (маркировка), OmniLink, Easy Label; POS-терминалы SKY-POS, кассы по 54-ФЗ, киоски самообслуживания, сканеры штрихкодов, ТСД, принтеры этикеток/чеков, электронные ценники, весы, дисплеи digital signage, промышленные планшеты. | I43: Бесплатная демо-версия Profi-T; партнёрская программа; упоминается возможность лизинга оборудования. Конкретных цен «от» и % скидок нет. | J43: Обратить внимание на их линейку киосков самообслуживания для ритейла — изучить как референс формата для розничных клиентов Simple Touch (например, интерактивные киоски для магазинов). | K43: YouTube PilotForRetail, VK @pilotrbs, Дзен — содержание не проверено детально. | L43: Уточнить | M43: C | N43: Проверить сайт вручную | O43: Проверено, данные изменены | P43: https://www.pilot.ru/ | Q43: Роль «Уточнить» → решить: партнёр по киоскам самообслуживания для ритейла (B) или вне фокуса (C)
A44: БС-Инжиниринг | B44: Прочее | C44: bs-group.pro | D44: 5027237616 | E44: =INDEX(База!$E:$E,51) -> 510 | F44: МО | G44: Профиль неочевиден — уточнить на сайте | H44: Уточнить | I44: Уточнить | J44: — | K44: Не проверено — открыть сайт, найти иконки соцсетей, оценить частоту постов | L44: Уточнить | M44: C | N44: Проверить сайт вручную | O44: Сайт не соответствует компании (bs-group.pro — производитель автодомов и спецавтомобилей, не связан с мультимедиа/АВ-интеграцией) | Q44: На bs-group.pro другая компания — найти правильный сайт по ИНН 5027237616
A45: СиВиДжи Аудио | B45: Вендор | C45: cvg.ru | D45: 7743714689 | E45: =INDEX(База!$E:$E,52) -> 506 | F45: Москва | G45: CVGAUDIO (СиВиДжи Аудио) — российский производитель профессионального звукового оборудования: фоновое озвучивание и речевое оповещение. | H45: Встраиваемые/потолочные/настенные акустические системы; 30+ моделей усилителей (100V и низкоомные линии); DSP-процессоры ZONER Pro; управление питанием Power Logic; контроллеры WEB-DRIVE; сабвуферы; сенсорные панели TSP-4; кабельная продукция PROCASTcable. | I45: Типовые пакетные решения; продажи также через Яндекс.Маркет, Ozon, Wildberries. Конкретных цен «от», скидок или гарантии с цифрами на сайте нет. | J45: Нет прямой применимой идеи; можно отметить присутствие на маркетплейсах (Яндекс.Маркет, Ozon, Wildberries) как дополнительный канал продаж для Simple Touch. | K45: Telegram t.me/cvgaudio, YouTube, VK, Rutube — содержание не проверено детально. | L45: Низкая релевантность | M45: C | N45: Изучить партнёрские условия на сайте | O45: Проверено, данные изменены | P45: https://cvg.ru/ ; https://t.me/cvgaudio
A46: ЛАНКЕЙ | B46: Широкопрофильный | C46: lankey.ru | D46: 9705008196 | E46: =INDEX(База!$E:$E,53) -> 491 | F46: Москва | G46: LanKey — российский ИТ-провайдер (20+ лет, 5000+ клиентов), аккредитация Минцифры: облачные и инженерные ИТ-решения для 15+ отраслей. | H46: Облачные сервисы (серверы, почта, ВКС/IP-телефония, 1С-хостинг, резервное копирование, DRaaS); ИТ-аудит и консалтинг; аутсорсинг; инженерные системы — связь, безопасность, электроснабжение, пожарная защита, мультимедиа, автоматизация. | I46: Конкретных цен «от», скидок, гарантии или акций на сайте нет. | J46: Нет на сайте — явной применимой идеи не найдено. | K46: Соцсетей на сайте нет. | L46: Заказчик субподряда / WL-производства | M46: B | N46: Выйти на руководителя AV-направления или закупки; предложить WL-производство нестандартных конструкций с гарантией до 5 лет | O46: Проверено 25.09.2026 | P46: https://lankey.ru/
A47: Энжи | B47: Дистрибьютор | C47: anzhee.ru | D47: 9722034090 | E47: =INDEX(База!$E:$E,54) -> 481 | F47: Москва | G47: Энжи (Anzhee) — российский производитель/дистрибьютор профессионального сценического (свет/звук) оборудования, один из лидеров рынка. | H47: Световое оборудование (LED-прожекторы, театральный свет, вращающиеся головы, пиксельные трубы, эффекты); звуковые системы (акустика, усилители, микшеры, радиосистемы); генераторы спецэффектов (дым, конфетти, CO2); бренды YME, Robe, DTS и др. | I47: Бесплатная консультация и подбор пакета оборудования за 24 часа с расчётом стоимости и схемой размещения (по онлайн-анкете); гарантийный и постгарантийный ремонт, удалённая поддержка. | J47: Перенять идею бесплатного подбора комплектации за 24 часа по онлайн-анкете — сделать похожий быстрый сервис расчёта конфигурации экранов/киосков Simple Touch под объект клиента. | K47: Соцсетей на сайте нет. | L47: Низкая релевантность | M47: C | N47: Запросить дилерские условия и сравнить с закупкой через Шанхай | O47: Проверено, данные изменены | P47: https://anzhee.ru/
A48: ИНТЕР | B48: Дистрибьютор | C48: inter.ru | D48: 7813210938 | E48: =INDEX(База!$E:$E,55) -> 442 | F48: Санкт-Петербург | G48: Дистрибьютор профессионального AV-оборудования, продаёт через сеть интеграторов и дилеров | H48: Дисплеи, проекторы, LED, ВКС, коммутация (бренды — уточнить на сайте) | I48: Дилерские цены, демо-фонд, обучение и сертификация партнёров, проектная поддержка | J48: Взять механику партнёрки: уровни партнёров, демо-фонд, обучение — и адаптировать для дизайнеров/агентств | K48: Не проверено — открыть сайт, найти иконки соцсетей, оценить частоту постов | L48: Поставщик / бенчмарк партнёрской программы | M48: C | N48: Запросить дилерские условия и сравнить с закупкой через Шанхай | O48: Сайт не открывается (ошибка 403 / «inter.ru недоступен», проверено через WebFetch и браузер) | Q48: Сайт не открылся — проверить вручную или найти актуальный домен по ИНН; колонки G–K сейчас шаблонные, не факты
A49: ГРОМВИЖН | B49: Интегратор АВ | C49: gromvision.ru | D49: 7720700150 | E49: =INDEX(База!$E:$E,56) -> 389 | F49: Москва | G49: Громвижн — интегратор мультимедийных систем: «разработка, поставка и реализация проектов под ключ по всей России», опыт более 15 лет. | H49: Видеостены (LCD/LED), светодиодные экраны, ВКС, интерактивное оборудование, контроллеры видеостен, конференц-залы и ситуационные центры | I49: Эксклюзивная цена для дилеров/партнёров (без цифр), оперативные поставки, полный пакет документов, обучение и сертификация, техподдержка. Точных цен, % скидок и сроков гарантии на сайте нет | J49: У Громвижн партнёрская страница построена на общих словах без цифр — Simple Touch может выигрывать конкретными процентами скидок и уровнями партнёрства прямо на сайте | K49: VK vk.com/gromvision\_msk, YouTube, RuTube, Дзен dzen.ru/gromvision — активность не детализирована (Telegram не найден) | L49: Партнёр: покупатель LED / киосков / стендов под своим брендом (WL) | M49: A | N49: Звонок собственнику/коммерческому: WL-производство LED-экранов, киосков, корпусов под их бренд по дилерской цене | O49: Проверено, данные изменены | P49: https://gromvision.ru/ ; https://gromvision.ru/partners | Q49: Открыть VK/Telegram вручную: дата последнего поста, частота, 2–3 темы
A50: Софит Лайт | B50: Музей, развлечения | C50: sofitlight.ru | D50: 7722244432 | E50: =INDEX(База!$E:$E,57) -> 369 | F50: Москва | G50: Софит Лайт — проектирование, поставка, монтаж и производство технологического (свет/звук/видео) оборудования для театров, концертных залов, спорта и парков развлечений; на рынке с 2001 г. Не студия контента для музеев. | H50: Световое оборудование (EK Lights, Compulite и др.), пульты управления светом, видеооборудование (Unilumin, Panasonic, SpinetiX), звук (Outline, HLA), интерком, лебедки (Coreat) | I50: Нет на сайте: цен, скидок, акций — только форма «Запросить предложение». Сертификат ISO 9001, гарантийное и постгарантийное обслуживание | J50: Компания не музейный контент-студия, а дистрибьютор техоборудования для сцены/спорта (Остров Мечты, Театр Эстрады) — пересмотреть роль: скорее канал сбыта LED-видеооборудования, чем партнёр по контенту | K50: Telegram t.me/sofitlight — канал почти пустой (2 участника, постов не видно). Также VK vk.com/sofit\_light, YouTube, RuTube, Дзен dzen.ru/sofitlight — активность не детализирована | L50: Дистрибьютор техоборудования для сцены/спорта (не контент-студия) — канал сбыта видеооборудования | M50: B | N50: Уточнить у них возможность поставки LED-экранов/видеостен Simple Touch как альтернативы Unilumin в их проекты | O50: Проверено, данные изменены | P50: https://sofitlight.ru/ ; https://t.me/s/sofitlight | Q50: Тип → «Театры, сцена»: не музейная студия, а поставщик сцен. оборудования
A51: БС-ГРУП | B51: Широкопрофильный | C51: bs-group.info | D51: 7730181560 | E51: =INDEX(База!$E:$E,58) -> 367 | F51: Москва | G51: ИТ-интегратор; AV/мультимедиа — одно из направлений (переговорные, видеостены, ситуационные центры) | H51: Видеостены, LED, ВКС, ситуационные центры, СКС, ИТ-инфраструктура | I51: Комплексный проект «под ключ»: аудит → проект → поставка → монтаж → сервис; тендеры 44/223-ФЗ | J51: Страница «Для интеграторов» на сайте: производство нестандартных корпусов, стоек, LED-конструкций и брендирования под их проекты (White Label) | K51: Не проверено — открыть сайт, найти иконки соцсетей, оценить частоту постов | L51: Заказчик субподряда / WL-производства | M51: B | N51: Выйти на руководителя AV-направления или закупки; предложить WL-производство нестандартных конструкций с гарантией до 5 лет | O51: Сайт не открывается (сайт в разработке — заглушка WordPress, содержательной информации нет) | Q51: Сайт не открылся — проверить вручную или найти актуальный домен по ИНН; колонки G–K сейчас шаблонные, не факты
A52: Смарткиоск | B52: Вендор | C52: smartkiosk.ru | D52: 5032294024 | E52: =INDEX(База!$E:$E,59) -> 358 | F52: МО | G52: SMARTKIOSK — российский производитель интерактивных киосков и терминалов самообслуживания (моделей Solo, Kristall) и интерактивных столов; собственная разработка и производство. | H52: Интерактивные киоски Solo (32/43/55"), Kristall (43/49/65"), интерактивные столы Solo (32/43"), информационные киоски, аренда оборудования, разработка кастомных моделей под проект. | I52: Гарантия до 36 месяцев; аренда киосков; разработка индивидуальных моделей под ТЗ; техподдержка включена. Цен «от» на сайте нет. | J52: Сравнить гарантию: у Simple Touch — до 5 лет против 36 мес у SMARTKIOSK; использовать более длинную гарантию как конкурентное преимущество в презентациях и продажах. | K52: Соцсетей на сайте нет. | L52: Прямой конкурент (киоски) | M52: A (мониторинг) | N52: Тайный покупатель: КП на 10 киосков 43" с брендированием | O52: Проверено 25.09.2026 | P52: https://smartkiosk.ru/
A53: INTOKU (ИНТОКУ) | B53: Театры, сцена | C53: intoku.ru | D53: 7704489895 | E53: =INDEX(База!$E:$E,60) -> 358 | F53: Москва | G53: Сценическое оборудование: свет, звук, механика для театров и площадок | H53: Световое и звуковое оборудование, сценическая механика | I53: Проект и оснащение сцены под ключ | J53: — | K53: Не проверено — открыть сайт, найти иконки соцсетей, оценить частоту постов | L53: Низкая релевантность | M53: C | N53: Не тратить время сейчас | O53: Сайт не открывается (ошибка SSL-сертификата — «Ошибка нарушения конфиденциальности» в браузере, также 404 через WebFetch) | Q53: Сайт не открылся — проверить вручную или найти актуальный домен по ИНН; колонки G–K сейчас шаблонные, не факты
A54: АудиоВидеоСистемы | B54: Интегратор АВ | C54: audioprofi.ru | D54: 6658426261 | E54: =INDEX(База!$E:$E,61) -> 336 | F54: Екатеринбург | G54: АудиоВидеоСистемы — федеральный мультимедийный интегратор (с 2006 г.): оснащение конференц-залов, диспетчерских/ситуационных центров, актовых залов и аудиторий «под ключ»; 59 регионов присутствия. | H54: Видеоотображение и LED-экраны/медиафасады, конференцсвязь/ВКС, концертная акустика, сценический свет, интерактивные технологии, фоновая трансляция звука | I54: Оборудование по цене производителя, выездная демонстрация/тест-драйв оборудования у клиента, лизинг/рассрочка/кредит, 3D-визуализация проекта, КП за 1 день, гарантия 12 мес. с подменным фондом, работа по 44-ФЗ/223-ФЗ | J54: Выездной тест-драйв оборудования и 3D-визуализация проекта — сильные приёмы вовлечения; Simple Touch стоит внедрить аналогичную выездную демонстрацию и визуализацию проекта до продажи | K54: VK vk.com/av\_syst — активность не детализирована; общий Telegram-контакт менеджера (не канал). Более 2500 проектов, 5 наград ProIntegration Awards 2026 — сильное портфолио для гостендеров | L54: Партнёр: покупатель LED / киосков / стендов под своим брендом (WL) | M54: A | N54: Звонок собственнику/коммерческому: WL-производство LED-экранов, киосков, корпусов под их бренд по дилерской цене | O54: Проверено, данные изменены | P54: https://audioprofi.ru/ | Q54: Открыть VK/Telegram вручную: дата последнего поста, частота, 2–3 темы
A55: РИВА | B55: Дистрибьютор | C55: riwa.ru | D55: 7719890620 | E55: =INDEX(База!$E:$E,64) -> 330 | F55: Москва | G55: RIWA — московский дистрибьютор/интегратор проф. АВ-оборудования для переговорных (20 лет, 638 проектов, 12 зарубежных поставщиков). | H55: Конференц-системы (проводные/беспроводные/мультимедиа); синхронный перевод; ВКС; PTZ-камеры; системы голосования; направленные колонки; LED-видеостены; звук и микрофоны; коммутация; запись/стриминг; интерактивное оборудование; выдвижные мониторы. | I55: Техконсалтинг и аудит проектов; поддержка госзакупок (44-ФЗ/223-ФЗ); аренда оборудования (конференц-системы, перевод, голосование); партнёрская программа; учебный центр; гарантийное обслуживание. | J55: Перенять формат учебного центра для обучения работе с оборудованием — организовать похожее обучение для интеграторов/партнёров по продукции Simple Touch. | K55: Соцсетей на сайте нет. | L55: Поставщик / бенчмарк партнёрской программы | M55: C | N55: Запросить дилерские условия и сравнить с закупкой через Шанхай | O55: Проверено, данные изменены | P55: https://riwa.ru/
A56: АВРОРА/Сонорусс | B56: Вендор | C56: sonoruss.ru | D56: 7714866077 | E56: =INDEX(База!$E:$E,65) -> 314 | F56: Москва | G56: Сонорусс — дистрибьютор и инженерное подразделение по проф. оборудованию для культурных, спортивных и общественных объектов: звук, свет, LED-экраны. | H56: L-Acoustics (звук, серии X/S/A/K/L, сабвуферы); Ayrton (сценический свет, лазерно-фосфорные источники); Arenalux (LED-экраны — внутренние, наружные, гибкие, прозрачные); M2 Technology (управление звуком и экранами). | I56: Конкретных цен «от», скидок, гарантии или акций на сайте нет. | J56: Обратить внимание на линейку прозрачных LED-экранов Arenalux — изучить как референс для расширения продуктовой линейки Simple Touch. | K56: Telegram t.me/sonoruss, VK vk.com/sonorussaudio — содержание не проверено детально. | L56: Низкая релевантность | M56: C | N56: Изучить партнёрские условия на сайте | O56: Проверено, данные изменены | P56: https://sonoruss.ru/ ; https://t.me/sonoruss
A57: ПМТ | B57: Музей, развлечения | C57: pmt.ru | D57: 5040147369 | E57: =INDEX(База!$E:$E,66) -> 299 | F57: МО | G57: СмартЛаб (pmt.ru) — проектирование и производство кинетических инсталляций и мультимедийных решений для публичных пространств и выставочных стендов. | H57: Кинетические инсталляции, интерактивные мультимедийные инсталляции, мультипространства «под ключ», выставочные стенды, XR/VR/AR-решения, инсталляции в аренду | I57: Нет на сайте: прайс-листов, гарантийных сроков, демо. Только форма «Заявка на проект» с ответом в течение нескольких часов (10:00-19:00 МСК) | J57: Обещание быстрого ответа на заявку (несколько часов) — Simple Touch может использовать похожий SLA-оффер как отличие от медленных конкурентов | K57: Telegram t.me/pmt\_multimedia — содержание не детализировано. VK/YouTube/Дзен/Rutube/Habr на сайте не найдены | L57: Партнёр: у нас производство LED/интерактива для их экспозиций | M57: A | N57: Предложить связку: они — концепция и контент, Simple Touch — корпуса, киоски, LED, МАФ, стенды | O57: Проверено 25.09.2026 | P57: https://pmt.ru/ ; https://pmt.ru/portfolio | Q57: Открыть VK/Telegram вручную: дата последнего поста, частота, 2–3 темы
A58: АВ ПРО | B58: Интегратор АВ | C58: av-pro.info | D58: 1659188885 | E58: =INDEX(База!$E:$E,67) -> 291 | F58: Казань | G58: АВ ПРО (Казань) — системный интегратор мультимедийных и интерактивных решений для конференц-залов, образования, театров и госорганизаций. | H58: Звуковое оборудование (микрофоны, усилители, консоли), проекторы и LED-экраны, интерактивные дисплеи, ВКС и видеозахват, системы синхронного перевода, световое/архитектурное оборудование, Digital Signage | I58: Нет на сайте: цен, скидок, сроков гарантии, бесплатного выезда/демо, партнёрской программы | J58: Нет открытых офферов — предложить типовой пакет «переговорная S/M/L» с фикс-ценой как региональному партнёру в Казани | K58: Telegram t.me/av\_pro, VK vk.com/avprokzn, YouTube, Яндекс Дзен — активность не детализирована | L58: Партнёр: покупатель LED / киосков / стендов под своим брендом (WL) | M58: A | N58: Региональный партнёр/дилер: WL-производство + дилерская цена | O58: Проверено 25.09.2026 | P58: https://av-pro.info/ | Q58: Открыть VK/Telegram вручную: дата последнего поста, частота, 2–3 темы
A59: Эмерлинк | B59: Бродкаст | C59: emerlink.net | D59: 7730104245 | E59: =INDEX(База!$E:$E,68) -> 286 | F59: Москва | G59: Эмерлинк — российский разработчик оборудования и ПО для кодирования, мультиплексирования и доставки цифрового ТВ-контента. | H59: Аппаратные платформы Emerlink (Compact/Platform); портативное оборудование (Video 2.0/3.0, Encoder Mini); сетевое оборудование (SAT, PRO); ПО для кодирования/декодирования, доставки видео (ADS), мониторинга, транскодирования и мультиплексирования. | I59: Цены не публичны — только через заявку/коммерческое предложение. Конкретных цен «от», скидок или гарантии с цифрами на сайте нет. | J59: Нет на сайте — не пересекается с профилем Simple Touch, явной применимой идеи не найдено. | K59: Telegram t.me/atrpassociation, Rutube rutube.ru/channel/47589089 — содержание не проверено детально. | L59: Низкая релевантность | M59: C | N59: Не тратить время сейчас | O59: Проверено 25.09.2026 | P59: https://emerlink.net/
A60: Аллегри | B60: Вендор | C60: ??? | D60: 7727570341 | E60: =INDEX(База!$E:$E,69) -> 281 | F60: Москва | G60: Сайт не указан — вероятно, связан с ПК Аллегри; уточнить | H60: Собственная продукция — уточнить на сайте | I60: Партнёрская программа для интеграторов (проверить) | J60: Оценить: можно ли встроить их продукт в наши экраны/киоски как комплект | K60: Не проверено — открыть сайт, найти иконки соцсетей, оценить частоту постов | L60: Потенциальный технологический партнёр | M60: B | N60: Изучить партнёрские условия на сайте | O60: Требует ручной проверки (сайт не указан в колонке C; возможно дублирует ПК Аллегри, allegri-group.ru — уточнить у составителя) | Q60: Сайт не указан: найти по ИНН 7727570341, проверить, не дубль ли это «ПК Аллегри» (строка выше)
A61: IP Video Systems | B61: Дистрибьютор | C61: ipvs.ru | D61: 7714606600 | E61: =INDEX(База!$E:$E,70) -> 269 | F61: Москва | G61: IP Video Systems — московский дистрибьютор АВ-решений: поставка, монтаж и настройка проекционного оборудования (700+ проектов). | H61: Комплекты для переговорных; камеры ВКС (PTZ, videobar); спикерфоны; ЖК-панели, LED-экраны, интерактивные панели; микрофоны/радиосистемы; звук и усилители; сетевое оборудование; системы управления; мебель. | I61: Прайс-лист доступен (Google Sheets); бесплатная консультация по телефону/обратный звонок; работа по 44-ФЗ/223-ФЗ; гарантия и техподдержка; продажи также на Ozon и Яндекс.Маркет. | J61: Перенять идею публичного прайс-листа в открытом доступе (Google Sheets) — повышает прозрачность и доверие клиентов при выборе оборудования Simple Touch. | K61: VK vk.com/ipvs\_ru, YouTube — содержание не проверено детально. | L61: Низкая релевантность | M61: C | N61: Запросить дилерские условия и сравнить с закупкой через Шанхай | O61: Проверено, данные изменены | P61: https://ipvs.ru/
A62: СитиМедиа | B62: Прочее | C62: sitimedia.ru | D62: 5258105649 | E62: =INDEX(База!$E:$E,71) -> 267 | F62: Нижний Новгород | G62: СитиМедиа — нижегородский интернет-магазин проекционного и интерактивного оборудования для бизнеса, бюджетных организаций и образования. | H62: Проекторы и аксессуары, интерактивные доски/панели, ЖК/LED-дисплеи, документ-камеры, экраны, сенсорные киоски и интерактивные столы, оборудование ВКС, робототехника, 3D-принтеры, VR, крепления и мебель. | I62: Демо-шоурум для показа оборудования; аренда оборудования на разный срок; готовые интерактивные комплекты для школ; спецусловия для бюджетных/образовательных организаций; поддержка тендеров и госзакупок; официальная гарантия производителя. | J62: Перенять формат демо-шоурума и готовых «коробочных» комплектов для конкретных сегментов (например, готовый комплект интерактивного киоска под музей/шоурум) — упростить выбор для клиента. | K62: VK vk.com/sitimediaedu, Rutube rutube.ru/channel/59236552 — содержание не проверено детально (VK не открывается инструментом проверки). | L62: Возможный региональный партнёр | M62: B | N62: Проверить сайт вручную | O62: Проверено, данные изменены | P62: https://sitimedia.ru/
A63: Интэч Инкорпорейтед | B63: Интегратор АВ | C63: intechirs.ru | D63: 7726429875 | E63: =INDEX(База!$E:$E,72) -> 258 | F63: Москва | G63: Интэч Инкорпорейтед (INTECHIRS Inc.) — производитель мультимедийных решений «любого масштаба»: проектирование, поставка, монтаж и сервис по всей России; с 2018 г., 3038+ клиентов. | H63: LED-экраны (indoor/outdoor, разные геометрии), интерактивные панели 65"/75" 4K, интерактивные киоски и столы, системы электронной очереди, монтаж/ремонт/техподдержка, аренда и лизинг | I63: Бесплатная доставка по РФ (0 руб.), расчёт КП за 2 часа, 100% постоплата, 375+ сервисных центров по России (круглосуточно), работа по 44-ФЗ/223-ФЗ. Точных цен «от» в открытом доступе нет — расчёт через форму | J63: У Intechirs — расчёт КП за 2 часа и постоплата 100% (без предоплаты) — сильные конкурентные офферы; Simple Touch стоит рассмотреть аналогичный быстрый расчёт и гибкую оплату | K63: Telegram t.me/Intechirs\_Inc — активность не детализирована. Также аккаунт в MAX. VK/YouTube/Дзен/Rutube/Habr не найдены | L63: Прямой конкурент (производитель LED-экранов, панелей и киосков — не только интегратор) | M63: A (мониторинг) | N63: Тайный покупатель: запросить КП на интерактивную панель 75" и экран 3×2 м — сравнить сроки (2 часа), цену и условия оплаты | O63: Проверено, данные изменены | P63: https://intechirs.ru/ ; https://t.me/s/Intechirs\_Inc | Q63: Тип → «Светодиодка/производитель»: заявляют производство; КП за 2 часа и 100% постоплата — в бенчмарк
A64: СМАРТ АВ | B64: Дистрибьютор | C64: smart-av.ru | D64: 7726453620 | E64: =INDEX(База!$E:$E,73) -> 246 | F64: Москва | G64: Smart-AV — российский системный интегратор мультимедийных и AV-решений: проектирование, подбор оборудования, монтаж и сервис для переговорных и презентационных пространств. | H64: Конференц-камеры (PTZ/4K/360°), спикерфоны и микрофонные массивы, интерактивные панели/LED/LCD-экраны, проекторы, звуковое оборудование, ВКС-терминалы, системы бронирования, акустические кабины. | I64: Бесплатный тест-драйв оборудования; бесплатный онлайн-конфигуратор переговорной с 3D-визуализацией (бета); бесплатный выезд/консультация; работают только с брендами с полной гарантией в РФ; поддержка 44-ФЗ/223-ФЗ. Цен «от» нет. | J64: Перенять идею бесплатного 3D-конфигуратора переговорной — сделать аналогичный онлайн-инструмент подбора и визуализации интерактивных панелей/LED-экранов Simple Touch под пространство клиента. | K64: VK vk.com/smartavvks, Rutube rutube.ru/channel/52282548, публикации на VC.ru и Habr (habr.com/ru/companies/smartav\_multimedia) — активность и темы не детализированы (VK не открылся инструментом проверки). | L64: AV-интегратор без собственного производства — вероятный потенциальный партнёр, а не производитель-конкурент | M64: A | N64: Обсудить партнёрство: предложить включить оборудование Simple Touch (LED-экраны, киоски, интерактивные панели) в портфель их интеграционных проектов | O64: Проверено, данные изменены | P64: https://smart-av.ru/ | Q64: Открыть VK/Telegram вручную: дата последнего поста, частота, 2–3 темы
A65: Полианалитика | B65: Прочее | C65: polyanalitika.ru | D65: 7727457593 | E65: =INDEX(База!$E:$E,75) -> 246 | F65: Москва | G65: ПолиАналитика — российский разработчик/интегратор BI и аналитических решений на отечественном ПО для ситуационных центров, госсектора и корпораций. | H65: Polyflow (сбор/ETL данных), POLYHUB (аналитический хаб), POLYCORE (аналитическое ядро), Visiology (российская BI-платформа), техподдержка и мониторинг, разработка решений под ситуационные центры. | I65: Конкретных цен «от», скидок, гарантии или акций на сайте нет. | J65: Нет прямой применимой идеи для продукта; можно отметить формат участия в отраслевых форумах (агротех, ИТ-форумы) как канал продвижения для Simple Touch. | K65: Telegram t.me/polyanalitika — активен, посты неск. раз/месяц (последние — сентябрь 2026): участие в форумах (агрокогресс, ProIT), ИИ в ситуационных центрах, BI+LLM для госуправления. VK, YouTube, Rutube тоже есть, не детализированы. | L65: Партнёр для ситуационных центров | M65: B | N65: Проверить сайт вручную | O65: Проверено, данные изменены | P65: https://polyanalitika.ru/ ; https://t.me/s/polyanalitika
A66: Банана Брэд | B66: Музей, развлечения | C66: bananabread.pro | D66: 9717055592 | E66: =INDEX(База!$E:$E,77) -> 229 | F66: Москва | G66: BananaBread — creative engineering studio («команда дизайн-мыслителей превращает пространства в впечатления»); офисы в Москве и Дубае. | H66: Интерактивные инсталляции для музеев, мультимедиа-шоу и видеомэппинг, музейные интерактивные приложения (карты, инфокарты), апгрейд экспозиционных витрин, инженерные/IT-решения для пространств | I66: Нет на сайте цен и акций — только контакты для брифинга (letsbake@bananabread.pro, +7 499 390 0705) | J66: Кейсы: Еврейский музей (интерактивная карта Домов Хабад), Музей «Динамо» (зона «Стань Динамовцем», мультимедиа-шоу с видеомэппингом) — предложить связку: они контент, Simple Touch — производство | K66: YouTube и Vimeo указаны в футере сайта (без прямых текстовых URL). Telegram/VK не найдены | L66: Конкурент в музеях + партнёр (у них контент, у нас производство) | M66: A | N66: Предложить связку: они — концепция и контент, Simple Touch — корпуса, киоски, LED, МАФ, стенды | O66: Проверено 25.09.2026 | P66: https://bananabread.pro/
A67: ФИЛИН ПРО | B67: Музей, развлечения | C67: filin.pro | D67: 7722421339 | E67: =INDEX(База!$E:$E,78) -> 223 | F67: Москва | G67: FILIN — мультимедийные решения для презентаций товаров и имиджевых проектов: интерактивные выставочные стенды, музеи, инсталляции; 13 лет, 250+ клиентов, 400+ проектов. | H67: Мультимедийные выставочные стенды, интерактивные музеи, интерактивные инсталляции, разработка контента, интерактивные учебные классы | I67: Нет на сайте: цен, скидок, гарантий. Предложение — презентация компании, обратный звонок, полный цикл «под ключ» | J67: Сильные кейсы (ММК, «Дом полимеров» СИБУР, ВДНХ, выставка «Россия», Еврейский музей) без открытых цен — предложить связку: они контент, Simple Touch — производство корпусов/киосков/LED | K67: Telegram t.me/filin\_office, VK vk.com/filin\_multimedia, YouTube — активность не детализирована | L67: Конкурент в музеях + партнёр (у них контент, у нас производство) | M67: A | N67: Предложить связку: они — концепция и контент, Simple Touch — корпуса, киоски, LED, МАФ, стенды | O67: Проверено 25.09.2026 | P67: https://filin.pro/ | Q67: Открыть VK/Telegram вручную: дата последнего поста, частота, 2–3 темы
A68: Лоджик Системс | B68: Широкопрофильный | C68: logic-systems.ru | D68: 7734668490 | E68: =INDEX(База!$E:$E,79) -> 223 | F68: Москва | G68: Logic Systems — российский ИТ-интегратор (с 2004 г.): поставка оборудования, системная интеграция и инфраструктура для бизнеса и госсектора; собственная сборка серверов/ПК. | H68: Серверы/СХД/сетевое оборудование известных брендов; лицензии ПО; заказная разработка (автоматизация, Big Data, блокчейн, ML); инженерные системы (ЦОД, видеонаблюдение, СКУД, ВКС); мультимедиа (переговорные, видеостены, виртуальные киоски для образования/коммерции); сборка серверов/ПК (до 1000 ПК и 100 серверов в месяц). | I68: Отсрочка платежа; тех.консультации до и после продажи; гарантия до 3 лет на собранное оборудование. Цен «от» на сайте нет. | J68: Сравнить гарантию: у Simple Touch — до 5 лет против 3 лет у Logic Systems на собственную сборку; использовать более длинную гарантию как аргумент в продажах и презентациях. | K68: Соцсетей на сайте нет. | L68: Заказчик субподряда / WL-производства | M68: B | N68: Выйти на руководителя AV-направления или закупки; предложить WL-производство нестандартных конструкций с гарантией до 5 лет | O68: Проверено, данные изменены | P68: https://logic-systems.ru/
A69: Метаформа | B69: Музей, развлечения | C69: meta-forma.ru | D69: 7839120735 | E69: =INDEX(База!$E:$E,80) -> 206 | F69: Санкт-Петербург | G69: Бюро музейной сценографии «Метаформа» (СПб/Москва) — «комплекс услуг по созданию музеев под ключ»: концепция, экспозиции, корпоративные музеи, временные выставки; заявлено собственное производство. | H69: Создание музеев «с нуля», музейные экспозиции, корпоративные музеи, временные выставки, интерактивные инсталляции, мультимедийный контент | I69: Нет на сайте: цен, скидок, гарантий. Оффер — 4-этапный процесс: концепция → проектирование → производство/реализация → техподдержка | J69: У Метаформы заявлено собственное производство — уточнить при контакте, действительно ли своё или на аутсорсе; если аутсорс — предложить Simple Touch как производственную базу для их экспозиций | K69: Telegram t.me/burometaforma, VK vk.com/burometaforma, YouTube, Behance — активность не детализирована | L69: Партнёр: у нас производство LED/интерактива для их экспозиций (уточнить — заявляют своё производство) | M69: A | N69: Предложить связку: они — концепция и контент, Simple Touch — корпуса, киоски, LED, МАФ, стенды | O69: Проверено 25.09.2026 | P69: https://meta-forma.ru/ | Q69: Открыть VK/Telegram вручную: дата последнего поста, частота, 2–3 темы
A70: Детектор (новые технологии) | B70: Светодиодка | C70: detectorgroup.ru | D70: 9705057490 | E70: =INDEX(База!$E:$E,81) -> 205 | F70: Москва | G70: Detector Group — системный интегратор мультимедиа с 2010 г.: LED-экраны и мультимедийные системы, своё конструкторское бюро и производство. | H70: Уличные/интерьерные/гибкие/прозрачные/COB LED-экраны, видеостены и медиафасады, видеополы и интерактивные дисплеи, проекторы, монтаж и сервис | I70: Цены от 25 000₽/м² (уличные), от 38 000₽/м² (интерьерные), от 40 000₽/м² (гибкие), от 55 000₽ (мобильные видеостены), от 60 000₽ (проекторы), видеостены от 50 000₽/ед. Калькулятор на сайте (/kalkulyator/). Гарантия и сроки не указаны | J70: У Detector Group детальная сетка цен «от» по типам экранов прямо на сайте — Simple Touch стоит сравнить свои цены и рассмотреть аналогичную открытую сетку по типам продукции | K70: Только контактная Telegram-ссылка (t.me/+79037909027, не канал). VK/YouTube/Дзен/Rutube/Habr не найдены | L70: Прямой конкурент (LED) | M70: A (мониторинг) | N70: Тайный покупатель: запросить КП на экран 3×2 м indoor и 6×3 м outdoor — сравнить цену, сроки, гарантию, подачу КП | O70: Проверено, данные изменены | P70: https://detectorgroup.ru/ ; https://detectorgroup.ru/kalkulyator/
A71: Полисервис | B71: Интегратор АВ | C71: polyservice.ru | D71: 7727355810 | E71: =INDEX(База!$E:$E,82) -> 203 | F71: Москва | G71: PolyService — IT-аккредитованный сервисный центр: обслуживание мультимедийного AV/IT-оборудования (Москва, СПб, регионы). Это сервисная компания, а не продавец проектов/оборудования. | H71: Сервисное обслуживание 24х7, гарантийный и постгарантийный ремонт, монтаж и пусконаладка, программирование систем управления, аудит и консалтинг, модернизация комплексов | I71: Выезд по заявке — 1 рабочий день; комплексные сервисные контракты с SLA; бесплатная консультация по заявке. Цены и скидки не опубликованы | J71: Компания — сервисный подрядчик, не закупщик оборудования под своим брендом — переоценить роль: скорее потенциальный партнёр по сервисному обслуживанию наших инсталляций, чем WL-покупатель | K71: Telegram-бот t.me/polymate\_ai\_bot (не канал). VK/YouTube/Дзен/Rutube/Habr не найдены | L71: Потенциальный сервисный субподрядчик для гарантийного обслуживания наших объектов (не покупатель WL) | M71: B | N71: Уточнить условия субподряда на сервисное обслуживание LED/интерактивных инсталляций в регионах | O71: Проверено, данные изменены | P71: https://polyservice.ru/ | Q71: Тип → «Сервис»: рассмотреть как подрядчика по гарантийному обслуживанию наших объектов в регионах
A72: ВидеоТрейд | B72: Бродкаст | C72: videotrade.ru | D72: 7713641585 | E72: =INDEX(База!$E:$E,83) -> 190 | F72: Москва | G72: ВидеоТрейд — московская инженерно-интеграционная компания: проектирование, поставка и внедрение мультимедийных систем «полного цикла». | H72: Системы управления и диспетчеризации (ситуационные центры, визуализация); дисплейные системы (экраны, LED, видеостены); инженерное проектирование (обследование, концепция, документация); интеграция и пусконаладка; звук и акустика; сервис и развитие систем. | I72: Конкретных цен «от», скидок, гарантии или акций на сайте нет — только приглашение обсудить проект. | J72: Нет на сайте — явной применимой идеи не найдено. | K72: Соцсетей на сайте нет. | L72: Низкая релевантность | M72: C | N72: Не тратить время сейчас | O72: Проверено 25.09.2026 | P72: https://videotrade.ru/
A73: АВ ПРОМ | B73: Интегратор АВ | C73: av-prom.ru | D73: 7716207129 | E73: =INDEX(База!$E:$E,84) -> 187 | F73: Москва | G73: АВ ПРОМ — проектирование и комплексное оснащение объектов видеостенами, системами отображения информации, мультимедийными и АВ-комплексами по всей России. | H73: Видеостены и LED-экраны, профессиональные дисплеи и ЖК-панели, конференц-системы и синхронный перевод, оснащение ТВ-студий, диспетчерские/ситуационные центры, звуковое оборудование | I73: Нет на сайте: цен, скидок, гарантии, бесплатного выезда/демо, партнёрской программы | J73: Нет соцсетей и открытых офферов — предложить типовой пакет «переговорная S/M/L» с фикс-ценой и сроком | K73: Соцсетей на сайте нет | L73: Партнёр: покупатель LED / киосков / стендов под своим брендом (WL) | M73: A | N73: Звонок собственнику/коммерческому: WL-производство LED-экранов, киосков, корпусов под их бренд по дилерской цене | O73: Проверено 25.09.2026 | P73: https://av-prom.ru/
A74: Умный Век | B74: Интегратор АВ | C74: umvek.ru | D74: 9729025070 | E74: =INDEX(База!$E:$E,85) -> 186 | F74: Москва | G74: Умный Век — проектирует и монтирует видеостены, LED-экраны, ВКС и ситуационные центры «под ключ»; на рынке с 2016 г. | H74: Видеостены и LED-экраны, ВКС, центры мониторинга, Digital Signage и корпоративное ТВ, профессиональный свет и звук, R\&D спецпроекты | I74: Бесплатная визуализация решений, лизинг на экраны, монтаж от 3 дней по России и СНГ, дополнительная гарантия и сервисное сопровождение. Точных цен на сайте нет | J74: У Умный Век есть лизинг на экраны и бесплатная визуализация — Simple Touch может добавить аналогичные офферы (лизинг, бесплатный 3D-рендер проекта) для конверсии | K74: Соцсетей на сайте нет | L74: Партнёр: покупатель LED / киосков / стендов под своим брендом (WL) | M74: A | N74: Звонок собственнику/коммерческому: WL-производство LED-экранов, киосков, корпусов под их бренд по дилерской цене | O74: Проверено, данные изменены | P74: https://umvek.ru/
A75: (без названия) | B75: Светодиодка | C75: sapphire-led.com | D75: 5024230595 | E75: =INDEX(База!$E:$E,86) -> 186 | F75: Москва | G75: SAPPHIRE — производство и продажа светодиодных рекламных экранов, полный цикл от проектирования до установки (Москва). | H75: LED-экраны серии SCI (высокая плотность пикселей), рекламные дисплеи, экраны для мероприятий, дисплеи для ТРЦ, проектирование и монтаж, сервис и гарантийное обслуживание | I75: Заявлены «конкурентоспособные цены и минимальные сроки» без цифр; калькулятора, точных цен за м² и сроков гарантии на сайте нет | J75: У Sapphire нет открытых цен/калькулятора — Simple Touch может выигрывать наглядным расчётом стоимости на сайте | K75: Соцсетей на сайте нет | L75: Прямой конкурент | M75: A (мониторинг) | N75: Тайный покупатель: запросить КП на экран 3×2 м indoor и 6×3 м outdoor — сравнить цену, сроки, гарантию, подачу КП | O75: Проверено 25.09.2026 | P75: https://sapphire-led.com/ | Q75: Вписать название «SAPPHIRE» в колонку A (и в «Базу»), проверить юрлицо по ИНН
A76: ИНТЕРАКТИВНЫЕ ЦИФРОВЫЕ РЕШЕНИЯ | B76: Интегратор АВ | C76: interactivedigital.ru | D76: 7727299604 | E76: =INDEX(База!$E:$E,87) -> 185 | F76: Москва | G76: Interactive Digital — разработка и внедрение инфраструктурных решений для бизнеса: мультимедиа, VR/AR, инженерные системы. Не подтверждено производство панелей/киосков/столов, как предполагалось ранее. | H76: Мультимедиа-системы (видео/аудио/свет), VR/AR-приложения, ситуационные центры и диспетчерские, конференц-залы, видеонаблюдение и контроль доступа, инженерные системы (электрика, кабельные сети, пожарная безопасность) | I76: Нет на сайте: цен, скидок, гарантийных сроков | J76: Профиль шире, чем «интерактивные киоски» — не факт, что прямой конкурент по железу; нужен звонок для уточнения, что именно производят/продают | K76: Соцсетей на сайте нет | L76: Интегратор широкого профиля (VR/AR, инженерные системы) — роль как конкурента в интерактиве не подтверждена, требует уточнения | M76: B | N76: Уточнить по телефону, производят ли они панели/киоски/столы сами, или это интеграция чужого оборудования — от этого зависит роль (конкурент vs WL-покупатель) | O76: Проверено, данные изменены | P76: https://interactivedigital.ru/
A77: Дикстен | B77: Интегратор АВ | C77: dixten.com | D77: 7743670583 | E77: =INDEX(База!$E:$E,89) -> 166 | F77: Москва | G77: DIXTEN — поставщик и инсталлятор профессионального AV-оборудования «под ключ» для госучреждений и бизнеса; 18+ лет, 700+ проектов по РФ с 2007 г. | H77: AV-решения для переговорных/конференц-залов, школьное оповещение, ВКС (партнёр МТС Линк), звук для кафе/фитнеса, музеи и выставки, актовые залы | I77: Бесплатная доставка по РФ, работа по 44-ФЗ/223-ФЗ/615-ФЗ, расчёт проекта от 3 часов, бесплатная консультация, каталог 50 000+ позиций от 880+ брендов и 50+ поставщиков | J77: У DIXTEN расчёт КП от 3 часов и огромный каталог (50 000+ позиций) — быстрый расчёт стоимости как конкурентный приём, который стоит перенять | K77: Telegram-бот t.me/dixtenbot, YouTube youtube.com/@DIXTEN\_PRO, RuTube — активность не детализирована | L77: Партнёр: покупатель LED / киосков / стендов под своим брендом (WL) | M77: A | N77: Звонок собственнику/коммерческому: WL-производство LED-экранов, киосков, корпусов под их бренд по дилерской цене | O77: Проверено, данные изменены | P77: https://dixten.com/ | Q77: Открыть VK/Telegram вручную: дата последнего поста, частота, 2–3 темы
A78: АН-Система | B78: Интегратор АВ | C78: ansystem.ru | D78: 6161094811 | E78: =INDEX(База!$E:$E,90) -> 166 | F78: Ростов-на-Дону | G78: АН-Система (Ростов-на-Дону) — разработка и реализация мультимедиа-проектов: оснащение аудиторий, конференц-залов и других помещений видео/аудио/управлением. | H78: Мультимедиа-проекты, ВКС и конгресс-системы, видеоотображение, звукоусиление и обработка звука, запись и трансляция, интегрированное управление | I78: Нет на сайте: цен, скидок, сроков гарантии (только «гарантийная поддержка» без цифр), демо, партнёрской программы | J78: Нет соцсетей и открытых офферов — региональный партнёр для юга России, предложить фикс-пакет «переговорная S/M/L» | K78: Соцсетей на сайте нет | L78: Партнёр: покупатель LED / киосков / стендов под своим брендом (WL) | M78: A | N78: Региональный партнёр/дилер | O78: Проверено 25.09.2026 | P78: https://ansystem.ru/
A79: Элиттех | B79: Дистрибьютор | C79: elittech.ru | D79: 7704660863 | E79: =INDEX(База!$E:$E,91) -> 165 | F79: Москва | G79: Элиттех — московский дистрибьютор проф. АВ-решений («поставщик исключительно надёжных видеорешений»), собственный бренд EliteBoard. | H79: Видеостены и панели, ТВ, интерактивные дисплеи/доски (EliteBoard), PTZ-камеры, проф. мониторы; звук (акустика, колонны, усилители); кабели и коммутация; контроллеры видеостен; AV over IP; решения для переговорных, образования, digital signage. | I79: Гарантия 3 года на EliteBoard; тройной контроль качества; бесплатные кабели при покупке контроллера (в акциях); демонстрации в шоуруме; прайс-листы в Excel для скачивания. | J79: Сравнить гарантию: у Simple Touch — до 5 лет против 3 лет у EliteBoard; перенять идею акции «бесплатный аксессуар при покупке» (кабели → например, крепление или ПО в подарок к экрану). | K79: Telegram t.me/elittech\_official, VK vk.com/elittechofficial — содержание не проверено детально. | L79: Поставщик / бенчмарк партнёрской программы | M79: C | N79: Запросить дилерские условия и сравнить с закупкой через Шанхай | O79: Проверено, данные изменены | P79: https://elittech.ru/ ; https://t.me/elittech\_official
A80: Онлайн Центр | B80: Интегратор АВ | C80: onlinecenter.ru | D80: 7736600352 | E80: =INDEX(База!$E:$E,93) -> 141 | F80: Москва | G80: OnlineCenter — внедрение цифровых технологий и оборудования для современных офисов: «повышаем продуктивность сотрудников в офисе и на удалёнке». | H80: Системы бронирования рабочих мест/переговорных, акустические кабины, мультимедиа (видеостены, экраны), контроль климата и обеззараживание воздуха, ВКС-оборудование, серверы и СХД | I80: Нет на сайте: цен, скидок, гарантии, демо, партнёрской программы — только форма «Подобрать решение» | J80: Нет соцсетей и офферов — компания больше про «умный офис» (бронирование, акустические кабины), чем классический AV-интегратор; предложить видеостены/LED как дополнение к их «умному офису» | K80: Соцсетей на сайте нет | L80: Партнёр: покупатель LED / киосков / стендов под своим брендом (WL) | M80: A | N80: Звонок собственнику/коммерческому: WL-производство LED-экранов, киосков, корпусов под их бренд по дилерской цене | O80: Проверено, данные изменены | P80: https://onlinecenter.ru/ | Q80: Профиль «умный офис», не классический AV — понизить до B
A81: AVISUAL | B81: Интегратор АВ | C81: avisual.ru | D81: 7707833088 | E81: =INDEX(База!$E:$E,94) -> 138 | F81: Москва | G81: AVISUAL — продажа мультимедийного оборудования с доставкой по Москве/РФ/СНГ; проектирование и внедрение AV-систем. | H81: Оборудование для конференций (микрофоны, камеры), аудиооборудование (усилители, акустика, сабвуферы), видеокоммутация и видеопроцессоры, интерактивные доски/экраны/столы, LED-экраны (indoor/outdoor), видеостены | I81: Нет на сайте: цен, скидок, гарантии, демо, партнёрской программы — только форма обратного звонка | J81: Нет соцсетей и офферов — предложить типовой пакет «переговорная S/M/L» с фикс-ценой | K81: Соцсетей на сайте нет | L81: Партнёр: покупатель LED / киосков / стендов под своим брендом (WL) | M81: A | N81: Звонок собственнику/коммерческому: WL-производство LED-экранов, киосков, корпусов под их бренд по дилерской цене | O81: Проверено 25.09.2026 | P81: https://avisual.ru/
A82: (без названия) | B82: — | C82: video-stena.ru | D82: 7722466700 | E82: =INDEX(База!$E:$E,95) -> 137 | F82: Москва | G82: ВидеоСтена — российский производитель и интегратор видеостен, LED-экранов и интерактивного оборудования (15+ лет на рынке). | H82: Бесшовные ЖК/LED-видеостены (Samsung, LG, COB, BOE); DLP-кубы; LED-экраны и медиафасады; интерактивные доски (линейки Business/Economy/Elite); интерактивные коммерческие дисплеи и киоски; OLED-витрины; контроллеры видеостен (MTG-1000 и др.); переговорные решения. | I82: Скидки до 40% на готовые бесшовные видеостены; контроллеры от 65 000 ₽; бесплатные консультации и расчёт конфигурации; партнёрская программа. | J82: Прямой конкурент по интерактивным киоскам и видеостенам — сравнить прайсинг (контроллеры от 65 000 ₽, скидки до 40%) и линейку продуктов для бенчмаркинга Simple Touch. | K82: Telegram @video\_stena — содержание не проверено детально. | L82: Производитель интерактивных киосков и видеостен — прямой конкурент | M82: A (мониторинг) | N82: Мониторить прайсинг и акции (скидки до 40%, контроллеры от 65 000 ₽) как бенчмарк | O82: Проверено, данные изменены | P82: https://video-stena.ru/ | Q82: Вписать название «ВидеоСтена», Тип → «Светодиодка» (производитель видеостен и киосков)
A83: Легион Проект | B83: Интегратор АВ | C83: legion-project.ru | D83: 7715748140 | E83: =INDEX(База!$E:$E,96) -> 130 | F83: Москва | G83: Легион Проект (Legion Group) — системный интегратор в области эргономики: инсталляция мультимедийного оборудования для ситуационных центров и диспетчерских, в т.ч. нефтегазовой отрасли. | H83: Ситуационные центры, диспетчерские пункты, центры сопровождения бурения (нефтегаз), залы совещаний и конференц-залы, системы кибербезопасности, аренда оборудования | I83: Нет на сайте: цен, скидок, гарантии, демо, партнёрской программы — только телефон и форма заявки | J83: Ниша в нефтегазовых центрах сопровождения бурения — узкая специализация, стоит предложить видеостены/LED под их профильные проекты | K83: Соцсетей на сайте нет | L83: Партнёр: покупатель LED / киосков / стендов под своим брендом (WL) | M83: A | N83: Звонок собственнику/коммерческому: WL-производство LED-экранов, киосков, корпусов под их бренд по дилерской цене | O83: Проверено 25.09.2026 | P83: https://legion-project.ru/
A84: Q Group | B84: Широкопрофильный | C84: kvantkm.ru | D84: 7715943158 | E84: =INDEX(База!$E:$E,97) -> 130 | F84: Москва | G84: Q Group — ИТ-интегратор, работает в России и Беларуси: сети, серверы/СХД, видеонаблюдение, ПК, инженерная инфраструктура, ПО. | H84: Сети и связь; серверы и системы хранения; видеонаблюдение; персональные компьютеры; инженерная инфраструктура; программные решения. | I84: Конкретных цен «от», скидок, гарантии или акций на сайте нет. | J84: Нет на сайте — явной применимой идеи не найдено. | K84: Telegram t.me/QGroupIT — канал без подписчиков и без видимых постов (пуст на момент проверки). Rutube rutube.ru/channel/55260579 — не детализирован. | L84: Заказчик субподряда / WL-производства | M84: B | N84: Выйти на руководителя AV-направления или закупки; предложить WL-производство нестандартных конструкций с гарантией до 5 лет | O84: Проверено 25.09.2026 | P84: https://kvantkm.ru/
A85: ТРИПЛАН | B85: Музей, развлечения | C85: triplan.ru | D85: 7701375152 | E85: =INDEX(База!$E:$E,98) -> 122.5 | F85: Москва | G85: ТриПлан — коммуникационная группа полного цикла в мультимедийных и коммуникационных технологиях: визуальные события, высокотехнологичное оборудование. | H85: 3D-маппинг-шоу (лазерные/проекционные), 3D-ковры CAMCARPETS для спортивных событий, аренда/продажа оборудования (проекторы, LED/голографические экраны), 3D-графика и контент, VR/MR, мобильные стенды | I85: Нет на сайте: цен, скидок, акций — только приглашение на консультацию | J85: Сильное портфолио на ВДНХ (стенды Самарской, Ставропольской области, «Город образования») — предложить связку: они шоу/контент, Simple Touch — производство стендов/LED | K85: YouTube youtube.com/channel/UC4VTqMAHMgVtBlpw1XC7blQ — активность не детализирована. Telegram/VK/Дзен/Rutube/Habr не найдены | L85: Конкурент в музеях + партнёр (у них контент, у нас производство) | M85: A | N85: Предложить связку: они — концепция и контент, Simple Touch — корпуса, киоски, LED, МАФ, стенды | O85: Проверено 25.09.2026 | P85: https://triplan.ru/ | Q85: Открыть VK/Telegram вручную: дата последнего поста, частота, 2–3 темы
A86: SubProject | B86: Интегратор АВ | C86: subproject.ru | D86: 9715397382 | E86: =INDEX(База!$E:$E,99) -> 113 | F86: Москва | G86: Системный интегратор аудиовизуальных систем: проектирование, поставка, монтаж, сервис | H86: Переговорные и конференц-залы, ВКС, видеостены, LED, звук, системы управления | I86: Проект «под ключ», типовые решения для переговорных, сервисный контракт | J86: Упаковать типовые пакеты «переговорная S/M/L» с фиксированной ценой и сроком | K86: Не проверено — открыть сайт, найти иконки соцсетей, оценить частоту постов | L86: Партнёр: покупатель LED / киосков / стендов под своим брендом (WL) | M86: A | N86: Звонок собственнику/коммерческому: WL-производство LED-экранов, киосков, корпусов под их бренд по дилерской цене | O86: Сайт не открывается (ошибка SSL-сертификата — истёк срок действия) | Q86: Сайт не открылся — проверить вручную или найти актуальный домен по ИНН; колонки G–K сейчас шаблонные, не факты
A87: Умные Технологии | B87: Интегратор АВ | C87: smt-tech.ru | D87: 7804652217 | E87: =INDEX(База!$E:$E,100) -> 113 | F87: Санкт-Петербург | G87: Умные Технологии (СПб) — интеграция и поставка мультимедийного оборудования: комплексное оснащение объектов АВ-системами «под ключ». | H87: AV-инсталляции и интерактив, Digital Signage, мультимедиа для музеев, переговорные и конференц-залы, ситуационные центры, LED-экраны (indoor/outdoor) | I87: Нет на сайте: цен, скидок, сроков гарантии, демо, партнёрской программы — только общие фразы «оптимальные сроки» | J87: Нет соцсетей и офферов — предложить типовой пакет «переговорная S/M/L» с фикс-ценой и сроком | K87: Соцсетей на сайте нет | L87: Партнёр: покупатель LED / киосков / стендов под своим брендом (WL) | M87: A | N87: Звонок собственнику/коммерческому: WL-производство LED-экранов, киосков, корпусов под их бренд по дилерской цене | O87: Проверено 25.09.2026 | P87: https://smt-tech.ru/
A88: Викинг Проект | B88: Интегратор АВ | C88: viking.ru | D88: 7802534070 | E88: =INDEX(База!$E:$E,102) -> 111 | F88: Санкт-Петербург | G88: Викинг Проект (СПб) — комплексное оснащение диспетчерских, конференц-залов, музейных экспозиций, ситуационных центров и переговорных; интеграция, поставка, обслуживание и аренда AV-оборудования. | H88: Мультимедийные проекторы, профессиональные дисплеи и видеостены, проекционные экраны, музейные экспозиции, аренда оборудования, сервис и ремонт | I88: Нет на сайте: цен, скидок, гарантии, демо, партнёрской программы — только контактные телефоны | J88: Нет офферов на сайте — предложить типовой пакет «переговорная S/M/L» и производство под их музейные экспозиции | K88: VK vk.com/club202631182, YouTube — активность не детализирована. Telegram/Дзен/Rutube/Habr не найдены | L88: Партнёр: покупатель LED / киосков / стендов под своим брендом (WL) | M88: A | N88: Звонок собственнику/коммерческому: WL-производство LED-экранов, киосков, корпусов под их бренд по дилерской цене | O88: Проверено 25.09.2026 | P88: https://viking.ru/ | Q88: Открыть VK/Telegram вручную: дата последнего поста, частота, 2–3 темы
A89: Акустические технологии | B89: Интегратор АВ | C89: amtrus.ru | D89: 5405302721 | E89: =INDEX(База!$E:$E,103) -> 108 | F89: Новосибирск | G89: АМТ-Групп (Новосибирск) — группа компаний полного цикла проектных, строительных и инженерных работ (генподряд); не классический AV-интегратор, как предполагалось. | H89: Строительство полного цикла (генподряд), театрально-концертные технологии, чистые помещения (медицина), архитектурная акустика и звукоизоляция, многофункциональные интерьеры, архитектурное проектирование | I89: Нет на сайте: цен, скидок, гарантии — только бесплатная консультация/обратный звонок | J89: Компания — строительный генподрядчик, а не покупатель LED/AV-оборудования напрямую; переоценить роль — скорее возможный субподрядчик по акустике для наших театральных проектов, чем WL-покупатель | K89: VK vk.com/amtdesign, Одноклассники ok.ru/group/59016504737841 — активность не детализирована. Telegram/YouTube/Дзен/Rutube/Habr не найдены | L89: Генподрядчик строительства (театры, чистые помещения) — не прямой покупатель AV/LED, роль уточняется | M89: B | N89: Уточнить, привлекают ли AV-оборудование как субподрядчики в своих проектах, или это чисто стройка/инженерка | O89: Проверено, данные изменены | P89: https://amtrus.ru/ | Q89: Генподрядчик — понизить приоритет до C
A90: СМАРТ РУМС | B90: Интегратор АВ | C90: smart-rooms.ru | D90: 9701033160 | E90: =INDEX(База!$E:$E,104) -> 106 | F90: Москва | G90: SMART ROOMS — внедрение и сопровождение мультимедийных решений для переговорных и конференц-залов; с 2015 г. | H90: Типовые конфигурации переговорных SMR 100-700, ВКС (софт и железо), видеоотображение и видеостены, звукоусиление и конференц-системы, монтаж и ПНР, проектирование | I90: Цены от 159 000₽ (рабочее место) до 5 800 000₽ (конференц-зал), фиксированная цена без изменений по ходу проекта, внедрение от 1 рабочего дня, гарантия производителей, бесплатный расчёт проекта | J90: У SMART ROOMS готовая линейка из 7 типовых пакетов SMR 100-700 с открытыми ценами от 159 000₽ — точная реализация идеи «переговорная S/M/L» с фикс-ценой, взять за образец | K90: Telegram t.me/Incomf, WhatsApp — активность не детализирована | L90: Партнёр: покупатель LED / киосков / стендов под своим брендом (WL) | M90: A | N90: Звонок собственнику/коммерческому: WL-производство LED-экранов, киосков, корпусов под их бренд по дилерской цене | O90: Проверено, данные изменены | P90: https://smart-rooms.ru/ | Q90: Открыть VK/Telegram вручную: дата последнего поста, частота, 2–3 темы
A91: СПИНЕТИКС | B91: Вендор | C91: dstools.ru | D91: 7735151538 | E91: =INDEX(База!$E:$E,106) -> 104 | F91: Москва | G91: DSTOOLS/SpinetiX Russia («Цифровые вывески») — разработчик ПО для digital signage и официальный сервис-партнёр SpinetiX в РФ (с 2007 г.). | H91: 123CMS (система управления контентом), медиаплееры EMP-III (4К, сети до 1000+ экранов) и iBX440 (для видеостен/LED, 4 синхр. HDMI-выхода); оборудование SpinetiX — склад, гарантия, ремонт; 250+ виджетов; создание контента; обучение (academy.dstools.ru). | I91: 6 месяцев кастомизации 123CMS включено; партнёрская программа с партнёрским порталом (project.dstools.ru); RMA и полный мониторинг сети. Цен «от» на сайте нет. | J91: Перенять концепцию интерактивных навигационных киосков (wayfinding) и решений для корпоративных музеев, которые SpinetiX продвигает на выставках — предложить готовый пакет «киоск + CMS-контент» для музейных/корпоративных пространств Simple Touch. | K91: Telegram t.me/spinetix — активен, посты неск. раз/неделю (последние \~15-17.09.2026): выставка Light+Audio Tec 2026, конференция по корпоративному мультимедиа, тема корпоративных музеев. VK spinetixrussia — не детализирован. | L91: Технологический партнёр (контент для экранов) | M91: B | N91: Изучить партнёрские условия на сайте | O91: Проверено, данные изменены | P91: https://dstools.ru/ ; https://t.me/s/spinetix
A92: БЛС | B92: Интегратор АВ | C92: bls-pro.ru | D92: 6685164199 | E92: =INDEX(База!$E:$E,107) -> 102 | F92: Екатеринбург | G92: БЛС (BLS) — российский мультимедийный интегратор (15+ лет, 24+ города РФ): проекты «под ключ» от идеи до реализации, 500+ проектов. | H92: Мультимедиа для переговорных, концертных залов и театров; видеостены и LED-экраны; интерактивные доски/панели; проекторы; звуковые системы; медиафасады; видеонаблюдение; digital signage; 3D-мэппинг; более 17 000 товаров в каталоге. | I92: Проектирование от 100 000 ₽; поставка и комплексные пакеты — «цена по согласованию»; бесплатные консультации экспертов; сертификация Extron и iRidi. | J92: Перенять модель прозрачной входной цены на проектирование («от 100 000 ₽») как формат прайсинга для консультационных/проектных услуг Simple Touch — снижает порог входа для клиента. | K92: Telegram t.me/kpk669, Rutube rutube.ru/channel/49183451 — содержание не проверено детально. | L92: Партнёр: покупатель LED / киосков / стендов под своим брендом (WL) | M92: B | N92: Звонок собственнику/коммерческому: WL-производство LED-экранов, киосков, корпусов под их бренд по дилерской цене | O92: Проверено, данные изменены | P92: https://bls-pro.ru/
A93: ОПТИМУС КОНСАЛТ | B93: Интегратор АВ | C93: optimusconsult.ru | D93: 7717716792 | E93: =INDEX(База!$E:$E,108) -> 98 | F93: Москва | G93: Optimus Consult — московский интегратор образовательных технологий (с 2012 г.): решения для поддержки учебного процесса. | H93: Гибридные аудитории «под ключ»; видеостудии для образования; платформы дистанционного обучения (Panopto); проекторы, интерактивные доски, видеостены, звук, камеры, компьютеры; проектирование и монтаж. | I93: Бесплатное тестирование оборудования; спецусловия для образовательных учреждений; сертифицированный монтаж по международным стандартам; работа с 44-ФЗ/223-ФЗ. Цен «от» и % скидок на сайте нет. | J93: Перенять офер «бесплатное тестирование оборудования перед покупкой» — предлагать образовательным/корпоративным клиентам тестовый период для интерактивных панелей/киосков Simple Touch. | K93: Соцсетей на сайте нет. | L93: Партнёр: покупатель LED / киосков / стендов под своим брендом (WL) | M93: B | N93: Звонок собственнику/коммерческому: WL-производство LED-экранов, киосков, корпусов под их бренд по дилерской цене | O93: Проверено, данные изменены | P93: https://optimusconsult.ru/
A94: Эддреалити | B94: Вендор | C94: addreality.com | D94: 7841481440 | E94: =INDEX(База!$E:$E,109) -> 97 | F94: Санкт-Петербург | G94: Addreality — российская SaaS-платформа Digital Signage для управления контентом на экранах; заявляет рост продаж клиентов до 30%. | H94: Управление контентом на экранах, «умная» трансляция (погода/время/аудитория), видеоаналитика посетителей, прямая и programmatic-реклама, аудиооформление, корпоративное ТВ, медиаплеер Arenity Box | I94: 14 дней бесплатного доступа к полному функционалу, гибкие тарифы по числу устройств, партнёрская программа для дилеров/реселлеров, прайс-лист SaaS 2026 (по ссылке на Я.Диск) | J94: У Addreality понятная модель: бесплатный триал 14 дней + подписка по устройствам — Simple Touch может предложить пакет «экран + подписка на контент-платформу» как повторную выручку | K94: Telegram t.me/addreality\_professionals, VK vk.com/addreality, YouTube, LinkedIn — активность не детализирована | L94: Технологический партнёр | M94: A | N94: Запросить партнёрские условия: предустановка платформы в наши экраны и киоски | O94: Проверено 25.09.2026 | P94: https://addreality.com/ | Q94: Открыть VK/Telegram вручную: дата последнего поста, частота, 2–3 темы
A95: ДИСОФТ/МЭИ | B95: Светодиодка | C95: дисофт.рф | D95: 9722044395 | E95: =INDEX(База!$E:$E,110) -> 95 | F95: Москва | G95: ДИСОФТ (дисофт.рф) — «производитель и интегратор техники нового поколения»: LED-экраны и мультимедийное оборудование для актовых залов; огромный портфель госзаказов (вузы, школы, ДК, администрации). | H95: LED-экраны (indoor, кабинетные/монолитные, шаг пикселя 0.9-5мм), мультимедийное оборудование для актовых залов, ПО «Платформа Дисофт» (реестр Минцифры №17612), системы звука/ВКС, комплексный монтаж по всей РФ | I95: Гарантия от 3 лет на оборудование, несколько складов — оборудование в наличии под срочную закупку, 40 монтажников в штате + бригады по РФ, индивидуальный подбор под нестандартные задачи. Открытых цен на сайте нет | J95: У ДИСОФТ — собственное ПО в реестре Минцифры (№17612) — даёт преимущество в гостендерах (импортозамещение); Simple Touch стоит рассмотреть регистрацию своего ПО/продукции в реестре Минцифры | K95: Соцсети на сайте не найдены (только телефон/email) | L95: Прямой конкурент | M95: A (мониторинг) | N95: Тайный покупатель: запросить КП на экран 3×2 м indoor и 6×3 м outdoor — сравнить цену, сроки, гарантию (у них от 3 лет), подачу КП | O95: Проверено, данные изменены | P95: https://дисофт.рф/
A96: Дигитон Системс | B96: Дистрибьютор | C96: digiton.ru | D96: 7813380859 | E96: =INDEX(База!$E:$E,111) -> 94 | F96: Санкт-Петербург | G96: Дигитон Системс (СПб) — российский производитель оборудования и ПО для радио/ТВ-вещания (с 1990 г.), пионер отечественной автоматизации эфира. | H96: Эфирные пульты, FM-передатчики, IP-кодеки, микрофоны, студийная мебель, блоки питания; собственная линейка DIGILINE; ПО автоматизации SYNADYN; проектирование студий, акустический консалтинг, монтаж, обучение персонала, ремонт. | I96: Конкретных цен «от», скидок, гарантии или акций на сайте нет. | J96: Не пересекается с профилем Simple Touch — явной применимой идеи не найдено. | K96: Соцсетей на сайте нет. | L96: Поставщик / бенчмарк партнёрской программы | M96: C | N96: Запросить дилерские условия и сравнить с закупкой через Шанхай | O96: Проверено 25.09.2026 | P96: https://digiton.ru/
A97: MEDIASCREEN | B97: Светодиодка | C97: mediascreen.pro | D97: 7840101254 | E97: =INDEX(База!$E:$E,112) -> 88 | F97: Санкт-Петербург | G97: MediaScreen — проектирование и производство светодиодных экранов, медиафасадов и видеоэкранов «под ключ» с монтажом по всей РФ. | H97: Медиафасады для зданий/ТЦ, уличные видеоэкраны и витрины, интерьерные LED-экраны, напольные видеопилоны, бегущие строки и информационные дисплеи, проектирование/монтаж/сервис | I97: Уличные экраны от 120 000₽/м², интерьерные от 55 000₽/м²; гарантия 2 года. Примеры: экран 0,8×2,88м — от 55 000₽, медиафасад 3,84×5,92м — от 1 800 000₽, видеопилон 0,96×1,92м — от 204 000₽ | J97: У MediaScreen детальные цены «от» с примерами готовых конфигураций и итоговой суммой — Simple Touch стоит показывать не только цену за м², но и готовые примеры «размер → итоговая цена» | K97: Личный Telegram-контакт менеджера t.me/Alex007181 (не канал), WhatsApp. VK/YouTube/Дзен/Rutube/Habr не найдены | L97: Прямой конкурент | M97: A (мониторинг) | N97: Тайный покупатель: запросить КП на экран 3×2 м indoor и 6×3 м outdoor — сравнить цену, сроки, гарантию (у них 2 года), подачу КП | O97: Проверено, данные изменены | P97: https://mediascreen.pro/
A98: Вижен Сервис | B98: Интегратор АВ | C98: visiontm.ru | D98: 7839346059 | E98: =INDEX(База!$E:$E,113) -> 88 | F98: Санкт-Петербург | G98: Vixen Service (СПб) — интегратор LED-экранов, мультимедийных систем и архитектурной подсветки зданий; на рынке с 2003 г. | H98: LED-экраны (в т.ч. для стадионов), мультимедийные системы, архитектурная/художественная подсветка зданий, видеонаблюдение; полный цикл: проект, поставка, монтаж, запуск, обслуживание; работа с зарубежными поставщиками, растаможка. | I98: Конкретных цен «от», скидок, гарантии или акций на сайте нет. | J98: Крупный опыт инсталляций LED-экранов на стадионах (Газпром Арена, ЧМ-2018) — рассмотреть как канал для проектов Simple Touch в спортивной/зрелищной сфере, если есть пересечение по сегменту. | K98: Соцсетей на сайте нет. | L98: Партнёр: покупатель LED / киосков / стендов под своим брендом (WL) | M98: B | N98: Звонок собственнику/коммерческому: WL-производство LED-экранов, киосков, корпусов под их бренд по дилерской цене | O98: Проверено, данные изменены | P98: https://visiontm.ru/
A99: Plentystars | B99: Дистрибьютор | C99: plentystars.com | D99: 7724850622 | E99: =INDEX(База!$E:$E,114) -> 85 | F99: Москва | G99: Plentystars — дистрибьютор с добавленной стоимостью проф. АВ и unified communications решений для интеграторов и реселлеров (офисы в Армении и на Кипре). | H99: Решения для переговорных/митинг-румов; АВ-инфраструктура для конференц-центров; автоматизация и управление; видеостены и дисплеи (LED, видеопроцессоры); digital signage (брендинг, навигация); command & control для критичных сред. | I99: Конкретных цен «от», скидок, гарантии или акций на сайте нет. | J99: Компания вне российского рынка (Армения/Кипр) — прямой применимости к Simple Touch не найдено; возможный канал выхода на рынки СНГ/Армении при необходимости. | K99: Соцсетей на сайте нет. | L99: Поставщик / бенчмарк партнёрской программы | M99: C | N99: Запросить дилерские условия и сравнить с закупкой через Шанхай | O99: Проверено, данные изменены | P99: https://plentystars.com/
A100: Индико Трейд | B100: Интегратор АВ | C100: indikotrade.ru | D100: 7743902996 | E100: =INDEX(База!$E:$E,115) -> 82 | F100: Москва | G100: Индико Трейд — московский системный интегратор АВ-решений для бизнеса, образования и госорганизаций: полный цикл от проекта до монтажа. | H100: Проекторы (домашний кинотеатр, короткофокусные, 4K, лазерные), профессиональные дисплеи и интерактивные панели, акустика, оборудование ВКС, системы управления и коммутации (Crestron), digital signage, системы бронирования переговорных. | I100: Цены на сайте не публичны («обратитесь к менеджерам»); услуги проектирования, поставки и монтажа. Конкретных цен «от», скидок или гарантии с цифрами нет. | J100: Нет на сайте — явной применимой идеи не найдено. | K100: VK vk.com/hifi.acustic, YouTube — содержание не проверено детально. | L100: Партнёр: покупатель LED / киосков / стендов под своим брендом (WL) | M100: B | N100: Звонок собственнику/коммерческому: WL-производство LED-экранов, киосков, корпусов под их бренд по дилерской цене | O100: Проверено 25.09.2026 | P100: https://indikotrade.ru/
...

Sheet Выводы
A1: Сводка по проверенной таблице
A2: Всего компаний | B2: =COUNTA('Анализ >50 млн'!A2:A113) -> 112
A3: Проверено агентом (сайт открылся) | B3: =COUNTIF('Анализ >50 млн'!O2:O113,"Проверено*") -> 100
A4: Сайт не открылся / требует ручной проверки | B4: =COUNTIF('Анализ >50 млн'!O2:O113,"Сайт не*")+COUNTIF('Анализ >50 млн'!O2:O113,"Требует*") -> 12
A5: Приоритет A — партнёрство сейчас | B5: =COUNTIF('Анализ >50 млн'!M2:M113,"A") -> 27
A6: Приоритет A (мониторинг) — прямые конкуренты | B6: =COUNTIF('Анализ >50 млн'!M2:M113,"A (мониторинг)") -> 16
A7: Приоритет B | B7: =COUNTIF('Анализ >50 млн'!M2:M113,"B") -> 46
A8: Приоритет C | B8: =COUNTIF('Анализ >50 млн'!M2:M113,"C") -> 23
A9: Строк с пометкой «что доработать» | B9: =COUNTA('Анализ >50 млн'!Q2:Q113) -> 43
A11: Главные выводы после проверки
A12: 1. Рынок LED стал прозрачным по цене: Детектор, Экранпро, GTLight, MediaScreen публикуют цены «от» и калькуляторы. Закрытая цена теперь минус, а не норма.
A13: 2. Гарантия «до 5 лет» — уже не уникальна: у Экранпро 5 лет + 10 лет техподдержки, у GTLight до 5 лет. Отличие надо собирать из связки: своё производство + завод в Китае + ширина ассортимента + сервисные обязательства.
A14: 3. Скорость КП — новое поле конкуренции: 2 часа (Интэч), от 3 часов (DIXTEN), 1 день (АВС).
A15: 4. Средние AV-интеграторы почти все без цен, без офферов и без соцсетей — им нужен производитель под их бренд. Это главный канал партнёрки.
A16: 5. Музейные студии (Visuals, Банана Брэд, Филин, Триплан, ПМТ) — без собственного производства железа: лучшие партнёры для музейного направления.
A17: 6. Telegram в отрасли ведут единицы, и выигрывают те, кто постит фотоотчёты с объектов каждый день. Для личного бренда Андрея ниша почти свободна.
A19: План действий — на листе «Задачи». Цены и офферы конкурентов — на листе «Бенчмарк цен и офферов».

Sheet Бенчмарк цен и офферов
A1: Компания | B1: Что продаёт | C1: Цены на сайте | D1: Гарантия | E1: Калькулятор / скорость КП | F1: Офферы, которые стоит забрать
A2: Детектор (Detector Group) | B2: LED, видеостены | C2: от 25 000 ₽/м² улица, от 38 000 ₽/м² интерьер, от 40 000 ₽/м² гибкие; видеостены от 50 000 ₽/ед. | D2: нет на сайте | E2: Калькулятор на сайте | F2: Сетка цен «от» по каждому типу экрана
A3: ЭКРАНПРО | B3: LED, видеостены | C3: от 34 781 ₽/м² до 2 089 775 ₽/м² | D3: 5 лет + 10 лет бесплатной техподдержки | E3: Калькулятор; проект за 4 дня при наличии на складе | F3: Гарантия + длинная техподдержка как главный аргумент
A4: GTLight (Электронные Системы) | B4: LED, медиафасады | C4: от 14 000 ₽ бегущая строка, от 47 000 ₽/м² медиафасад, от 65 000 ₽/м² улица | D4: 1–5 лет по типу оборудования | E4: Калькулятор; производство от 7 дней | F4: Срок производства в оффере
A5: MediaScreen | B5: LED, медиафасады | C5: от 55 000 ₽/м² интерьер, от 120 000 ₽/м² улица; примеры «размер → цена» | D5: 2 года | E5: — | F5: Готовые примеры конфигураций с итоговой суммой
A6: 1000 Дюймов (zFlex) | B6: Видеостены, LED, киоски | C6: Цены в двух калькуляторах | D6: 3 года | E6: Калькулятор; −10% за заявку из калькулятора | F6: Лизинг от 24 599 ₽/мес; подарок к заказу до 05.10
A7: ВидеоСтена (video-stena.ru) | B7: Видеостены, LED, киоски | C7: Контроллеры от 65 000 ₽; скидки до 40% на готовые видеостены | D7: нет на сайте | E7: Бесплатный расчёт конфигурации | F7: Скидка на готовые решения со склада
A8: HD LED Tech (ЭЙЧДИ) | B8: LED, своё производство | C8: На сайте цен нет; акции без цифр | D8: нет на сайте | E8: Расчёт по заявке | F8: Регулярные акции («ценопад»), активный Telegram 1–2 поста/день
A9: Смарткиоск | B9: Киоски, интерактивные столы | C9: Нет | D9: до 36 мес. | E9: — | F9: Аренда киосков; модели под ТЗ
A10: SMART ROOMS | B10: Переговорные под ключ | C10: 7 пакетов SMR 100–700: от 159 000 ₽ до 5 800 000 ₽, фикс-цена | D10: гарантия производителей | E10: Внедрение от 1 рабочего дня | F10: Образец пакетов «переговорная S/M/L»
A11: Интэч (Intechirs) | B11: Мультимедиа, производство | C11: Нет | D11: — | E11: КП за 2 часа | F11: 100% постоплата, бесплатная доставка, 375+ сервисных центров
A12: DIXTEN | B12: AV под ключ | C12: Нет | D12: — | E12: Расчёт от 3 часов | F12: Бесплатная доставка по РФ
... A17: VISUALPOINT | B17: AV для школ, вузов | C17: Фикс «всё включено» | D17: есть | E17: Несколько вариантов бюджета | F17: Бесплатный выезд с замерами; TG с фотоотчётами несколько раз в день
A19: Источник: сайты компаний, проверка 25.09.2026 (колонки I и P листа «Анализ»). Цены и акции меняются — перед использованием в КП и рекламе перепроверить.

Sheet База
A1: Компания | B1: Тип | C1: сайт | D1: ИНН | E1: Выручка за 2023г, млн, | F1: Регион
A2: КРОК | B2: Широкопрофильный | C2: croc.ru | D2: 7701004101 | E2: 26652 | F2: Москва
A3: XCOM | B3: Широкопрофильный | C3: xcom.ru | D3: 7743553167 | E3: 15243 | F3: Москва
A4: ЛАНИТ | B4: Широкопрофильный | C4: lanit.ru | D4: 7727004113 | E4: 14416 | F4: Москва
A5: ЛАНИТ | B5: Широкопрофильный | C5: lanit.ru | D5: 7727004113 | E5: 14416 | F5: Москва
A6: СТЕП ЛОДЖИК | B6: Широкопрофильный | C6: step.ru | D6: 7730081654 | E6: 9322 | F6: Москва
A7: АУВИКС | B7: Дистрибьютор | C7: auvix.ru | D7: 7708651718 | E7: 8933 | F7: Москва
A8: АВИЛЕКС | B8: Интегратор АВ | C8: avilex.ru | D8: 7731625191 | E8: 4100 | F8: Москва
A9: Полимедиа | B9: Интегратор АВ | C9: polymedia.ru | D9: 9705117847 | E9: 3975 | F9: Москва
A10: Полимедиа | B10: Интегратор АВ | C10: polymedia.ru | D10: 9705117847 | E10: 3975 | F10: Москва
A11: Лайв Саунд | B11: Интегратор АВ | C11: livesound.ru | D11: 9724154876 | E11: 3182 | F11: Москва
A12: Аметист | B12: Широкопрофильный | C12: ametist.tech | D12: 7810819986 | E12: 3137 | F12: Санкт-Петербург
A13: СИТИСИ Кэпитал | B13: Дистрибьютор | C13: ctccapital.ru | D13: 6732026311 | E13: 2555
A14: ЛЕ-Интеграция | B14: Широкопрофильный | C14: leintegration.ru | D14: 7720820948 | E14: 2180 | F14: Москва
A15: ЦС Проект | B15: Интегратор АВ | C15: digis.ru | D15: 7709697296 | E15: 1991 | F15: Москва
A16: ЦС Проект | B16: Дистрибьютор | C16: digis.ru | D16: 7709697296 | E16: 1991 | F16: Москва
A17: Astronis | B17: Широкопрофильный | C17: astronis.ru | D17: 7703402732 | E17: 1953 | F17: Москва
A18: Оберон | B18: Широкопрофильный | C18: oberon-it.ru | D18: 7722283103 | E18: 1856 | F18: Москва
A19: Труконф | B19: Вендор | C19: trueconf.ru | D19: 9717098324 | E19: 1832 | F19: Москва
A20: Vkorpe | B20: Широкопрофильный | C20: vkorpe.ru | D20: 7810341266 | E20: 1575 | F20: Санкт-Петербург
A21: АБАК-2000 | B21: Широкопрофильный | C21: abak2000.ru | D21: 3445084000 | E21: 1355 | F21: Москва
A22: ИЦ Телеком-Сервис | B22: Широкопрофильный | C22: teleserv.ru | D22: 7736038341 | E22: 1340 | F22: Москва
A23: Profdisplay | B23: Дистрибьютор | C23: profdisplays.ru | D23: 9715207761 | E23: 1263 | F23: Москва
A24: ASCREEN | B24: Музей, развлечения | C24: ascreen.ru | D24: 7804472253 | E24: 1052 | F24: Санкт-Петербург
A25: ГИГАНТ | B25: Широкопрофильный | C25: gigant.ru | D25: 7720768984 | E25: 943 | F25: Москва
... A30: ЭЙЧДИ | B30: Светодиодка | C30: hdlt.ru | D30: 7724865932 | E30: 771 | F30: Москва
A31: ТЕХНОМЕДИА ГРУПП | B31: Интегратор АВ | C31: tmgroup.ru | D31: 6143088075 | E31: 767
A32: Д2 Групп | B32: Интегратор АВ | C32: d2group.ru | D32: 7707661897 | E32: 719 | F32: Москва
A33: Visuals | B33: Музей, развлечения | C33: visuals.ru | D33: 7730700872 | E33: 709 | F33: Москва
A34: П10 | B34: Светодиодка | C34: p10.ru | D34: 7723917306 | E34: 703 | F34: Москва
A35: Анкомп | B35: Интегратор АВ | C35: ancomp.ru | D35: 7717103901 | E35: 696 | F35: Москва
A36: Видео ЛЕНД | B36: Прокат/Эвенты | C36: videoland-pro.ru | D36: 7701704424 | E36: 678 | F36: Москва
A37: ДИЛ | B37: Интегратор АВ | C37: dil-it.ru | D37: 7710892703 | E37: 656 | F37: Москва
A38: ГК Спутник | B38: Широкопрофильный | C38: gksputnik.ru | D38: 7724418010 | E38: 651 | F38: Москва
A39: ПК Аллегри | B39: Вендор | C39: allegri-group.ru | D39: 7724413781 | E39: 645 | F39: Москва
A40: ICL SERVICES | B40: Широкопрофильный | C40: icl-services.com | D40: 7728897484 | E40: 620 | F40: Москва
A41: Лемьер | B41: Интегратор АВ | C41: lemier.ru | D41: 7720715213 | E41: 618 | F41: Москва
A42: Брюллов Консалтинг | B42: Дистрибьютор | C42: brullov.com | D42: 7729443187 | E42: 604 | F42: Москва
A43: Брюллов Консалтинг | B43: Дистрибьютор | C43: brullov.com | D43: 7729443187 | E43: 604 | F43: Москва
A44: Брюллов Консалтинг | B44: Дистрибьютор | C44: brullov.com | D44: 7729443187 | E44: 604 | F44: Москва
A45: Электронные Системы | B45: Светодиодка | C45: gtlamp.ru | D45: 4205176605 | E45: 580
A46: Future Vision | B46: Светодиодка | C46: future-vision.ru | D46: 6658436206 | E46: 545 | F46: Екатеринбург
A47: ОПЕН ВИЖН | B47: Широкопрофильный | C47: open-vision.ru | D47: 7726627740 | E47: 544 | F47: Москва
A48: ВИНТЕО | B48: Вендор | C48: vinteo.ru | D48: 2312200249 | E48: 535
A49: ВИНТЕО | B49: Вендор | C49: vinteo.ru | D49: 2312200249 | E49: 535
A50: Пилот | B50: Прочее | C50: www.pilot.ru | D50: 7726527350 | E50: 517 | F50: Москва
A51: БС-Инжиниринг | B51: Прочее | C51: bs-group.pro | D51: 5027237616 | E51: 510 | F51: МО
A52: СиВиДжи Аудио | B52: Вендор | C52: cvg.ru | D52: 7743714689 | E52: 506 | F52: Москва
A53: ЛАНКЕЙ | B53: Широкопрофильный | C53: lankey.ru | D53: 9705008196 | E53: 491 | F53: Москва
A54: Энжи | B54: Дистрибьютор | C54: anzhee.ru | D54: 9722034090 | E54: 481 | F54: Москва
A55: ИНТЕР | B55: Дистрибьютор | C55: inter.ru | D55: 7813210938 | E55: 442 | F55: Санкт-Петербург
A56: ГРОМВИЖН | B56: Интегратор АВ | C56: gromvision.ru | D56: 7720700150 | E56: 389 | F56: Москва
A57: Софит Лайт | B57: Музей, развлечения | C57: sofitlight.ru | D57: 7722244432 | E57: 369 | F57: Москва
A58: БС-ГРУП | B58: Широкопрофильный | C58: bs-group.info | D58: 7730181560 | E58: 367 | F58: Москва
A59: Смарткиоск | B59: Вендор | C59: smartkiosk.ru | D59: 5032294024 | E59: 358 | F59: МО
A60: INTOKU (ИНТОКУ) | B60: Театры, сцена | C60: intoku.ru | D60: 7704489895 | E60: 358 | F60: Москва
A61: АудиоВидеоСистемы | B61: Интегратор АВ | C61: audioprofi.ru | D61: 6658426261 | E61: 336 | F61: Екатеринбург
... A76: Полианалитика | B76: Прочее | C76: polyanalitika.ru | D76: 7727457593 | E76: 246 | F76: Москва
A77: Банана Брэд | B77: Музей, развлечения | C77: bananabread.pro | D77: 9717055592 | E77: =61+168 -> 229 | F77: Москва
A78: ФИЛИН ПРО | B78: Музей, развлечения | C78: filin.pro | D78: 7722421339 | E78: 223 | F78: Москва
A79: Лоджик Системс | B79: Широкопрофильный | C79: logic-systems.ru | D79: 7734668490 | E79: 223 | F79: Москва
A80: Метаформа | B80: Музей, развлечения | C80: meta-forma.ru | D80: 7839120735 | E80: 206 | F80: Санкт-Петербург
A81: Детектор (новые технологии) | B81: Светодиодка | C81: detectorgroup.ru | D81: 9705057490 | E81: 205 | F81: Москва
A82: Полисервис | B82: Интегратор АВ | C82: polyservice.ru | D82: 7727355810 | E82: 203 | F82: Москва
A83: ВидеоТрейд | B83: Бродкаст | C83: videotrade.ru | D83: 7713641585 | E83: 190 | F83: Москва
A84: АВ ПРОМ | B84: Интегратор АВ | C84: av-prom.ru | D84: 7716207129 | E84: 187 | F84: Москва
A85: Умный Век | B85: Интегратор АВ | C85: umvek.ru | D85: 9729025070 | E85: 186 | F85: Москва
B86: Светодиодка | C86: sapphire-led.com | D86: 5024230595 | E86: 186 | F86: Москва
A87: ИНТЕРАКТИВНЫЕ ЦИФРОВЫЕ РЕШЕНИЯ | B87: Интегратор АВ | C87: interactivedigital.ru | D87: 7727299604 | E87: 185 | F87: Москва
A88: Банана Брэд | B88: Музей, развлечения | C88: bananabread.pro | D88: 9717055592 | E88: 169 | F88: Москва
A89: Дикстен | B89: Интегратор АВ | C89: dixten.com | D89: 7743670583 | E89: 166 | F89: Москва
A90: АН-Система | B90: Интегратор АВ | C90: ansystem.ru | D90: 6161094811 | E90: 166 | F90: Ростов-на-Дону
A91: Элиттех | B91: Дистрибьютор | C91: elittech.ru | D91: 7704660863 | E91: 165 | F91: Москва
A92: Элиттех | B92: Дистрибьютор | C92: elittech.ru | D92: 7704660863 | E92: 165 | F92: Москва
A93: Онлайн Центр | B93: Интегратор АВ | C93: onlinecenter.ru | D93: 7736600352 | E93: 141 | F93: Москва
A94: AVISUAL | B94: Интегратор АВ | C94: avisual.ru | D94: 7707833088 | E94: 138 | F94: Москва
C95: video-stena.ru | D95: 7722466700 | E95: 137 | F95: Москва
A96: Легион Проект | B96: Интегратор АВ | C96: legion-project.ru | D96: 7715748140 | E96: 130 | F96: Москва
A97: Q Group | B97: Широкопрофильный | C97: kvantkm.ru | D97: 7715943158 | E97: 130 | F97: Москва
A98: ТРИПЛАН | B98: Музей, развлечения | C98: triplan.ru | D98: 7701375152 | E98: 122.5 | F98: Москва
A99: SubProject | B99: Интегратор АВ | C99: subproject.ru | D99: 9715397382 | E99: 113 | F99: Москва
A100: Умные Технологии | B100: Интегратор АВ | C100: smt-tech.ru | D100: 7804652217 | E100: 113 | F100: Санкт-Петербург
A101: SubProject | B101: Интегратор АВ | C101: subproject.ru | D101: 9715397382 | E101: 113 | F101: Москва
A102: Викинг Проект | B102: Интегратор АВ | C102: viking.ru | D102: 7802534070 | E102: 111 | F102: Санкт-Петербург
A103: Акустические технологии | B103: Интегратор АВ | C103: amtrus.ru | D103: 5405302721 | E103: 108 | F103: Новосибирск
A104: СМАРТ РУМС | B104: Интегратор АВ | C104: smart-rooms.ru | D104: 9701033160 | E104: 106 | F104: Москва
A105: СМАРТ РУМС | B105: Интегратор АВ | C105: smart-rooms.ru | D105: 9701033160 | E105: 106 | F105: Москва
A106: СПИНЕТИКС | B106: Вендор | C106: dstools.ru | D106: 7735151538 | E106: 104 | F106: Москва
A107: БЛС | B107: Интегратор АВ | C107: bls-pro.ru | D107: 6685164199 | E107: 102 | F107: Екатеринбург
... A125: Медиасистем ГРУП | B125: Прокат/Эвенты | C125: avms.ru | D125: 7704824984 | E125: 61 | F125: Москва
A126: АВ Клуб ПРО | C126: avclub.pro | D126: 7714916680 | E126: 54 | F126: Москва
A127: КВМ Технологии | B127: Интегратор АВ | C127: kvmtech.ru | D127: 7724812112 | E127: 53 | F127: Москва
A128: Вижуалпоинт | B128: Интегратор АВ | C128: visualpoint.ru | D128: 6166088096 | E128: 52 | F128: Ростов-на-Дону
A129: Инициум | B129: Интегратор АВ | C129: initium.ru | D129: 7707512824 | E129: 49 | F129: Москва
A130: АВИНТ | B130: Интегратор АВ | C130: avint.ru | D130: 7743897457 | E130: 47 | F130: Москва
A131: Вижуалидер | B131: Дистрибьютор | C131: visualeader.ru | D131: 7726639505 | E131: 47 | F131: Москва
A132: Lightdec | B132: Театры, сцена | C132: lightdec.ru | D132: 7743369320 | E132: 43 | F132: Москва
A133: Дигискай | B133: Вендор | C133: digisky.ru | D133: 7731468319 | E133: 41 | F133: Москва
A134: 8 Ом | B134: Интегратор АВ | C134: 8ohm.ru | D134: 6658329469 | E134: 39.5 | F134: Екатеринбург
A135: Luxury Engineering | B135: Домашка | C135: luxeng.ru | E135: 36 | F135: Москва
...

Sheet Финансы
B2: Затраты на площадку | C2: 100000
B3: Участники внесли денег
B4: Положительный баланс
B9: 1. Вносим сколько потратили
B10: 2. Вносим сколько все оплатили, часть людей оплатят больше, чем стоит участие. Эти деньги мы вписываем на поддержку сообщества. Фомируем положиьтельный баланс.
B11: 3. Формируем отдельный счет, на котором у нас есть положительный баланс. Он копится, потом тратится на какие-то нужды. Обсудить с Сашей возможно отдельный эксель пока что простой

Sheet Данные
B12: Тип
B13: Интегратор АВ
B14: Музей, развлечения
B15: Прокат/Эвенты
B16: Бродкаст
B17: Трансляции
B18: Светодиодка
B19: Широкопрофильный
B20: Вендор
B21: Дистрибьютор
B22: Театры, сцена
B23: Домашка
B24: Прочее
